{"obj_edit_time":"1717396696","blocks":[{"block_id":"C5sCdBPIUoGkc3xEWm1c1t2snOf","block_type":1,"children":["RgMsdw995oKuuDxKX2Ec1hkJnOf","UDONdkMZaoNZsuxYE80ckzapnSg"],"page":{"elements":[{"text_run":{"content":"投放系统","text_element_style":{"bold":false,"inline_code":false,"italic":false,"strikethrough":false,"underline":false}}}],"style":{"align":1}},"parent_id":""},{"block_id":"RgMsdw995oKuuDxKX2Ec1hkJnOf","block_type":999,"parent_id":"C5sCdBPIUoGkc3xEWm1c1t2snOf","undefined":{}},{"block_id":"UDONdkMZaoNZsuxYE80ckzapnSg","block_type":2,"parent_id":"C5sCdBPIUoGkc3xEWm1c1t2snOf","text":{"elements":[{"text_run":{"content":"","text_element_style":{"bold":false,"inline_code":false,"italic":false,"strikethrough":false,"underline":false}}}],"style":{"align":1,"folded":false}}}]}