{"obj_edit_time":"1708918065","blocks":[{"block_id":"FPELdtBfPoYO8MxuGm2cRZJunDc","block_type":1,"children":["FpTmdIq34oOX8lxGaLKcGUprnpg","YGnadkQGSoTz4MxJ7hEcqaT1ndh","RHuddehgIoYYC2x20Y9cmqk9nA3","WBb3dPBG0ofxHuxsHvsc6Y37nxb","K9Ajd8jeWosslpxpIT3cPkmMnuR","VkLtdYZr0ov0PCxO6TicPmmLnzf","V1ptdMAEwoCvanx0YorcdlC2nEd","FwaidDjB6oQinmxc41ocLKNdnpg","KPO2dSqx1o7bEExaf5hcPrBznng","ReqbdwhnjoxLP7xSSVfc1cIfn1c","TV0ddbgaiox5ybxw1CQcJYugnXm","LbZhd5W0Oo0zRLxxI9HcG3glnD9","BZt6drTR8oArpOxh5QKcXA2sndh","BhmTdPaFOoYkvExAemscUy9Lnye","HWlGdF2gMoPOTzx7LGUcoKR8nFc","KuCFdtCPPoN7irxHNvqc8MFqnWq","XMETdtDscoXceCxvyXgcVBnxn5g","NG0ndXmo8oVkBCxS6B6cGvwanLd","NzvIdJ9SOopUNtxrZtxc22yUnuw","O3pKdtTrBoKaPRxtxUDcpqSJnZg","QtlzdzGQMobDOSxjbsUcQxavnZg","XGBZd5PZsot27fxD6iIcpACbnle","FOVxdt2UVoTKJ7xm7uTcPNyDneh","Tj9CdBMezoCfX3xxhVxcSrHTnvh","BteydbvcsoeO3mxqmd5cuxIwnab","CFibdUCQMo5HX6xq5WhcJrhmnTh","VUpLdyCaro1BGxxL0cvcLSlsn5g","TiQAdZhFOorikfxqPGrcQlT4nBf","DGGfdJzwiocoF1xPWV3cAUG6n3d","YQ3jdIdyyo8KvAxflEWcxa46ncg","L6ubdNxIsoGk5Yxu9MZcyzG8nWh","TdaZdLLS9oec4CxngI4cGtKynld","QOrmdlzqtoYmRmxmsAqcnrESniQ","EkvVduji5om9r1xEpU0cMIhtnEh","G4tPdXGbyorb0zxDx6BcnSmrnlb","CcfcdDKuFoQsHbxDhA7c3YqunLb","PLgBdn9vroelXPxa0wNcVhT2nfd","Ym7ldlSLZo8ugwxNpMicjKhynlb","U1qAdvki2oXXEqx8OtAcfINpnqM","EHWodZipLoyEwexqPoBcYCyrnfl","MhgAdXgnAoW1ukxVklvcyX7mn9g","GJYAdGYBDoeDt3xUa3ocHzxvnNh","ZtLIdc02vorVvJxDunfc66Okn7g","Hkhod6I0pojqxbx4X22c5pebnpI","XxiddYtklo7sapxp7s0cVYvMn0c","NGg6d12OVo7KBkxbt6TcwKUrnUh","T2Txd0A55odMIQx7pQSchySlnnb","Lt95disbboTUTuxLJlCcxYFhnCf","A9qDdLyImoMTcExWXYcca2a9nJf","JZj9d8sWroglRax2ncHcjt2InHX","E5xKd0TuPoc1aQxwO5hc6sPjnqb","VKxud9mUcoiG2Sx6Pm1c9cWjnih","V5LkdliZHox9rAxwq9gcixTknQg","QhgodFn9ooXqDAxOuiCc0xmBnNe","H9rsdmLNNoC8CkxBcymcfDfunhc","EsUkdzzPTo3SvJx4gI1cssMpn4q","HDiGdK5GnoCrDHxOxi3cJCbXnfg","GlAud4U83ocD4sxwq3zcf4pmnrd","G8gOdzPgoofUOCxHaBOcK7c3nJe","NcridX2g3oGOc0xsEK9cPNUdnLc","Hb1sdeu7xojDvtxIf8vcqNVOnad","BP7CdBTMYodR5oxKgRqca9H8nBd","X0kFdhdoIo0kkexs3zxchBopnmc","Gzojdd7yXo2vgdxaUqYczPcjnid","JXRGdJ9OUotzIjx5ZFbcNvtDnre","GnHAdyZw8oT2R1xuvLjc6Xfwnoe","WBQwdpXFXorDDBxzONMclcTfnih","RF0cdLeqtoiMXlxkmGaclKZwnEg","Qz1EdkhwXoT1OCx0GihcqQIGnvc","JuSXdHFhZoya6Fxb9P7cnua5n3e","VYszdUkI3oaMeixhGvfcZUZRnkd","LRBJdEDkToeuDzxGhiccoix1noh","Sz4PdOsaloo23ExMcVPcSXN8nkh","VoiddVa5Moob1wxn1UAcEachnVc","JkzsdhDEqoczX0xORCWcUnKbncZ"],"page":{"elements":[{"text_run":{"content":"系統介紹","text_element_style":{"bold":false,"inline_code":false,"italic":false,"strikethrough":false,"underline":false}}}],"style":{"align":1}},"parent_id":""},{"block_id":"FpTmdIq34oOX8lxGaLKcGUprnpg","block_type":3,"heading1":{"elements":[{"text_run":{"content":"概述","text_element_style":{"bold":false,"inline_code":false,"italic":false,"strikethrough":false,"underline":false}}}],"style":{"align":1,"folded":false}},"parent_id":"FPELdtBfPoYO8MxuGm2cRZJunDc"},{"block_id":"YGnadkQGSoTz4MxJ7hEcqaT1ndh","block_type":2,"parent_id":"FPELdtBfPoYO8MxuGm2cRZJunDc","text":{"elements":[{"text_run":{"content":"Whale 會計系統提供了一套可以自動獲取數據源，按照預設的科目及分錄規則進行自動記帳，進而完成帳實核對，主要包含了科目設置、分錄規則設置、合併規則設置、會計分錄、科目餘額、科目明細帳、記帳數據源等功能","text_element_style":{"bold":false,"inline_code":false,"italic":false,"strikethrough":false,"underline":false}}}],"style":{"align":1,"folded":false}}},{"block_id":"RHuddehgIoYYC2x20Y9cmqk9nA3","block_type":3,"heading1":{"elements":[{"text_run":{"content":"会计中台流程说明","text_element_style":{"bold":false,"inline_code":false,"italic":false,"strikethrough":false,"underline":false}}}],"style":{"align":1,"folded":false}},"parent_id":"FPELdtBfPoYO8MxuGm2cRZJunDc"},{"block_id":"WBb3dPBG0ofxHuxsHvsc6Y37nxb","block_type":21,"diagram":{"diagram_type":1},"parent_id":"FPELdtBfPoYO8MxuGm2cRZJunDc"},{"block_id":"K9Ajd8jeWosslpxpIT3cPkmMnuR","block_type":3,"heading1":{"elements":[{"text_run":{"content":"務操作管理","text_element_style":{"bold":false,"inline_code":false,"italic":false,"strikethrough":false,"underline":false}}}],"style":{"align":1,"folded":false}},"parent_id":"FPELdtBfPoYO8MxuGm2cRZJunDc"},{"block_id":"VkLtdYZr0ov0PCxO6TicPmmLnzf","block_type":3,"heading1":{"elements":[{"text_run":{"content":"參數設置","text_element_style":{"bold":false,"inline_code":false,"italic":false,"strikethrough":false,"underline":false}}}],"style":{"align":1,"folded":false}},"parent_id":"FPELdtBfPoYO8MxuGm2cRZJunDc"},{"block_id":"V1ptdMAEwoCvanx0YorcdlC2nEd","block_type":19,"callout":{"background_color":6,"border_color":6,"emoji_id":"anchor"},"children":["MssRdune7oXA3Xxn6fzcJ9uNnXe"],"parent_id":"FPELdtBfPoYO8MxuGm2cRZJunDc"},{"block_id":"MssRdune7oXA3Xxn6fzcJ9uNnXe","block_type":2,"parent_id":"V1ptdMAEwoCvanx0YorcdlC2nEd","text":{"elements":[{"text_run":{"content":"業務參數設置 > 記賬參數","text_element_style":{"bold":false,"inline_code":false,"italic":false,"strikethrough":false,"underline":false}}}],"style":{"align":1,"folded":false}}},{"block_id":"FwaidDjB6oQinmxc41ocLKNdnpg","block_type":2,"parent_id":"FPELdtBfPoYO8MxuGm2cRZJunDc","text":{"elements":[{"text_run":{"content":"證券機構在使用會計中臺之前需要先進行記賬參數設置，包括科目屬性、會計科目、分錄規則、資金類型以及合併規則等設置。","text_element_style":{"bold":false,"inline_code":false,"italic":false,"strikethrough":false,"underline":false}}}],"style":{"align":1,"folded":false}}},{"block_id":"KPO2dSqx1o7bEExaf5hcPrBznng","block_type":4,"heading2":{"elements":[{"text_run":{"content":"科目屬性","text_element_style":{"bold":false,"inline_code":false,"italic":false,"strikethrough":false,"underline":false}}}],"style":{"align":1,"folded":false}},"parent_id":"FPELdtBfPoYO8MxuGm2cRZJunDc"},{"block_id":"ReqbdwhnjoxLP7xSSVfc1cIfn1c","block_type":2,"parent_id":"FPELdtBfPoYO8MxuGm2cRZJunDc","text":{"elements":[{"text_run":{"content":"在使用會計中臺前，券商需要配置會計屬性。","text_element_style":{"bold":false,"inline_code":false,"italic":false,"strikethrough":false,"underline":false}}}],"style":{"align":1,"folded":false}}},{"block_id":"TV0ddbgaiox5ybxw1CQcJYugnXm","block_type":27,"image":{"align":2,"height":1614,"token":"VLmgbUNTwo06PNxxyHccfQuon2b","width":3828},"parent_id":"FPELdtBfPoYO8MxuGm2cRZJunDc"},{"block_id":"LbZhd5W0Oo0zRLxxI9HcG3glnD9","block_type":2,"parent_id":"FPELdtBfPoYO8MxuGm2cRZJunDc","text":{"elements":[{"text_run":{"content":"操作按鈕說明","text_element_style":{"bold":true,"inline_code":false,"italic":false,"strikethrough":false,"underline":false}}}],"style":{"align":1,"folded":false}}},{"block_id":"BZt6drTR8oArpOxh5QKcXA2sndh","block_type":12,"bullet":{"elements":[{"text_run":{"content":"新建：可根據券商公司需求自定義會計科目屬性。","text_element_style":{"bold":false,"inline_code":false,"italic":false,"strikethrough":false,"underline":false}}}],"style":{"align":1,"folded":false}},"parent_id":"FPELdtBfPoYO8MxuGm2cRZJunDc"},{"block_id":"BhmTdPaFOoYkvExAemscUy9Lnye","block_type":12,"bullet":{"elements":[{"text_run":{"content":"編輯：對已經添加的科目屬性可以進行人工編輯。","text_element_style":{"bold":false,"inline_code":false,"italic":false,"strikethrough":false,"underline":false}}}],"style":{"align":1,"folded":false}},"parent_id":"FPELdtBfPoYO8MxuGm2cRZJunDc"},{"block_id":"HWlGdF2gMoPOTzx7LGUcoKR8nFc","block_type":12,"bullet":{"elements":[{"text_run":{"content":"刪除：對已經添加的科目屬性可以進行刪除。","text_element_style":{"bold":false,"inline_code":false,"italic":false,"strikethrough":false,"underline":false}}}],"style":{"align":1,"folded":false}},"parent_id":"FPELdtBfPoYO8MxuGm2cRZJunDc"},{"block_id":"KuCFdtCPPoN7irxHNvqc8MFqnWq","block_type":4,"heading2":{"elements":[{"text_run":{"content":"1.2 會計科目","text_element_style":{"bold":false,"inline_code":false,"italic":false,"strikethrough":false,"underline":false}}}],"style":{"align":1,"folded":false}},"parent_id":"FPELdtBfPoYO8MxuGm2cRZJunDc"},{"block_id":"XMETdtDscoXceCxvyXgcVBnxn5g","block_type":2,"parent_id":"FPELdtBfPoYO8MxuGm2cRZJunDc","text":{"elements":[{"text_run":{"content":"在配置科目屬性後，需要根據券商公司的要求配置會計科目。","text_element_style":{"bold":false,"inline_code":false,"italic":false,"strikethrough":false,"underline":false}}}],"style":{"align":1,"folded":false}}},{"block_id":"NG0ndXmo8oVkBCxS6B6cGvwanLd","block_type":27,"image":{"align":2,"height":1622,"token":"Pj7Fb49Rvo0Kl5xYgmvcrOwwnNc","width":3820},"parent_id":"FPELdtBfPoYO8MxuGm2cRZJunDc"},{"block_id":"NzvIdJ9SOopUNtxrZtxc22yUnuw","block_type":2,"parent_id":"FPELdtBfPoYO8MxuGm2cRZJunDc","text":{"elements":[{"text_run":{"content":"操作按鈕說明","text_element_style":{"bold":true,"inline_code":false,"italic":false,"strikethrough":false,"underline":false}}}],"style":{"align":1,"folded":false}}},{"block_id":"O3pKdtTrBoKaPRxtxUDcpqSJnZg","block_type":12,"bullet":{"elements":[{"text_run":{"content":"批量導入：如果券商公司需要大量添加會計科目，可以選擇批量導入，大批量新增會計科目。","text_element_style":{"bold":false,"inline_code":false,"italic":false,"strikethrough":false,"underline":false}}}],"style":{"align":1,"folded":false}},"parent_id":"FPELdtBfPoYO8MxuGm2cRZJunDc"},{"block_id":"QtlzdzGQMobDOSxjbsUcQxavnZg","block_type":12,"bullet":{"elements":[{"text_run":{"content":"新建：可根據券商公司需求单笔自定義會計科目。","text_element_style":{"bold":false,"inline_code":false,"italic":false,"strikethrough":false,"underline":false}}}],"style":{"align":1,"folded":false}},"parent_id":"FPELdtBfPoYO8MxuGm2cRZJunDc"},{"block_id":"XGBZd5PZsot27fxD6iIcpACbnle","block_type":12,"bullet":{"elements":[{"text_run":{"content":"編輯：對已經添加的会计科目可以進行人工編輯。","text_element_style":{"bold":false,"inline_code":false,"italic":false,"strikethrough":false,"underline":false}}}],"style":{"align":1,"folded":false}},"parent_id":"FPELdtBfPoYO8MxuGm2cRZJunDc"},{"block_id":"FOVxdt2UVoTKJ7xm7uTcPNyDneh","block_type":12,"bullet":{"elements":[{"text_run":{"content":"刪除：對已經添加的会计科目可以進行刪除。","text_element_style":{"bold":false,"inline_code":false,"italic":false,"strikethrough":false,"underline":false}}}],"style":{"align":1,"folded":false}},"parent_id":"FPELdtBfPoYO8MxuGm2cRZJunDc"},{"block_id":"Tj9CdBMezoCfX3xxhVxcSrHTnvh","block_type":4,"heading2":{"elements":[{"text_run":{"content":"1.3 分錄規則","text_element_style":{"bold":false,"inline_code":false,"italic":false,"strikethrough":false,"underline":false}}}],"style":{"align":1,"folded":false}},"parent_id":"FPELdtBfPoYO8MxuGm2cRZJunDc"},{"block_id":"BteydbvcsoeO3mxqmd5cuxIwnab","block_type":2,"parent_id":"FPELdtBfPoYO8MxuGm2cRZJunDc","text":{"elements":[{"text_run":{"content":"形成分錄之前需要根據券商公司實際業務需要配置對應的分錄規則。","text_element_style":{"bold":false,"inline_code":false,"italic":false,"strikethrough":false,"underline":false}}}],"style":{"align":1,"folded":false}}},{"block_id":"CFibdUCQMo5HX6xq5WhcJrhmnTh","block_type":27,"image":{"align":2,"height":1524,"token":"ESmSbOsTzoRK7jxkODlcsYSZnXf","width":3814},"parent_id":"FPELdtBfPoYO8MxuGm2cRZJunDc"},{"block_id":"VUpLdyCaro1BGxxL0cvcLSlsn5g","block_type":2,"parent_id":"FPELdtBfPoYO8MxuGm2cRZJunDc","text":{"elements":[{"text_run":{"content":"操作按鈕說明","text_element_style":{"bold":true,"inline_code":false,"italic":false,"strikethrough":false,"underline":false}}}],"style":{"align":1,"folded":false}}},{"block_id":"TiQAdZhFOorikfxqPGrcQlT4nBf","block_type":12,"bullet":{"elements":[{"text_run":{"content":"新增：可根據券商公司需求新增各業務的分錄規則。","text_element_style":{"bold":false,"inline_code":false,"italic":false,"strikethrough":false,"underline":false}}}],"style":{"align":1,"folded":false}},"parent_id":"FPELdtBfPoYO8MxuGm2cRZJunDc"},{"block_id":"DGGfdJzwiocoF1xPWV3cAUG6n3d","block_type":12,"bullet":{"elements":[{"text_run":{"content":"編輯：對已經添加的分录规则可以進行人工編輯。","text_element_style":{"bold":false,"inline_code":false,"italic":false,"strikethrough":false,"underline":false}}}],"style":{"align":1,"folded":false}},"parent_id":"FPELdtBfPoYO8MxuGm2cRZJunDc"},{"block_id":"YQ3jdIdyyo8KvAxflEWcxa46ncg","block_type":12,"bullet":{"elements":[{"text_run":{"content":"複製：可以將當前分錄規則進行復制，方便新增類似的分錄規則。","text_element_style":{"bold":false,"inline_code":false,"italic":false,"strikethrough":false,"underline":false}}}],"style":{"align":1,"folded":false}},"parent_id":"FPELdtBfPoYO8MxuGm2cRZJunDc"},{"block_id":"L6ubdNxIsoGk5Yxu9MZcyzG8nWh","block_type":12,"bullet":{"elements":[{"text_run":{"content":"刪除：對已經添加的分录规则可以進行刪除。","text_element_style":{"bold":false,"inline_code":false,"italic":false,"strikethrough":false,"underline":false}}}],"style":{"align":1,"folded":false}},"parent_id":"FPELdtBfPoYO8MxuGm2cRZJunDc"},{"block_id":"TdaZdLLS9oec4CxngI4cGtKynld","block_type":4,"heading2":{"elements":[{"text_run":{"content":"1.4 資金類型","text_element_style":{"bold":false,"inline_code":false,"italic":false,"strikethrough":false,"underline":false}}}],"style":{"align":1,"folded":false}},"parent_id":"FPELdtBfPoYO8MxuGm2cRZJunDc"},{"block_id":"QOrmdlzqtoYmRmxmsAqcnrESniQ","block_type":2,"parent_id":"FPELdtBfPoYO8MxuGm2cRZJunDc","text":{"elements":[{"text_run":{"content":"對於券商公司獲取的銀行賬單可以自定義資金類型。","text_element_style":{"bold":false,"inline_code":false,"italic":false,"strikethrough":false,"underline":false}}}],"style":{"align":1,"folded":false}}},{"block_id":"EkvVduji5om9r1xEpU0cMIhtnEh","block_type":27,"image":{"align":2,"height":1462,"token":"TopPbU9GCosOBdx3qzrc7SehnDe","width":3792},"parent_id":"FPELdtBfPoYO8MxuGm2cRZJunDc"},{"block_id":"G4tPdXGbyorb0zxDx6BcnSmrnlb","block_type":2,"parent_id":"FPELdtBfPoYO8MxuGm2cRZJunDc","text":{"elements":[{"text_run":{"content":"操作按鈕說明","text_element_style":{"bold":true,"inline_code":false,"italic":false,"strikethrough":false,"underline":false}}}],"style":{"align":1,"folded":false}}},{"block_id":"CcfcdDKuFoQsHbxDhA7c3YqunLb","block_type":12,"bullet":{"elements":[{"text_run":{"content":"新建：可根據券商公司銀行賬單新建不同資金類型標籤。","text_element_style":{"bold":false,"inline_code":false,"italic":false,"strikethrough":false,"underline":false}}}],"style":{"align":1,"folded":false}},"parent_id":"FPELdtBfPoYO8MxuGm2cRZJunDc"},{"block_id":"PLgBdn9vroelXPxa0wNcVhT2nfd","block_type":12,"bullet":{"elements":[{"text_run":{"content":"刪除：對已經添加的资金类型可以進行刪除。","text_element_style":{"bold":false,"inline_code":false,"italic":false,"strikethrough":false,"underline":false}}}],"style":{"align":1,"folded":false}},"parent_id":"FPELdtBfPoYO8MxuGm2cRZJunDc"},{"block_id":"Ym7ldlSLZo8ugwxNpMicjKhynlb","block_type":4,"heading2":{"elements":[{"text_run":{"content":"1.5 合併規則","text_element_style":{"bold":false,"inline_code":false,"italic":false,"strikethrough":false,"underline":false}}}],"style":{"align":1,"folded":false}},"parent_id":"FPELdtBfPoYO8MxuGm2cRZJunDc"},{"block_id":"U1qAdvki2oXXEqx8OtAcfINpnqM","block_type":2,"parent_id":"FPELdtBfPoYO8MxuGm2cRZJunDc","text":{"elements":[{"text_run":{"content":"如果券商公司導出的財務報表需要合併，則可以自定義合併規則。","text_element_style":{"bold":false,"inline_code":false,"italic":false,"strikethrough":false,"underline":false}}}],"style":{"align":1,"folded":false}}},{"block_id":"EHWodZipLoyEwexqPoBcYCyrnfl","block_type":27,"image":{"align":2,"height":1452,"token":"OL9KbJyoSoCtfCxXKPhcmFcjn8d","width":3834},"parent_id":"FPELdtBfPoYO8MxuGm2cRZJunDc"},{"block_id":"MhgAdXgnAoW1ukxVklvcyX7mn9g","block_type":2,"parent_id":"FPELdtBfPoYO8MxuGm2cRZJunDc","text":{"elements":[{"text_run":{"content":"操作按鈕說明","text_element_style":{"bold":true,"inline_code":false,"italic":false,"strikethrough":false,"underline":false}}}],"style":{"align":1,"folded":false}}},{"block_id":"GJYAdGYBDoeDt3xUa3ocHzxvnNh","block_type":12,"bullet":{"elements":[{"text_run":{"content":"新建：可根據券商公司需求新增報表的合併規則。","text_element_style":{"bold":false,"inline_code":false,"italic":false,"strikethrough":false,"underline":false}}}],"style":{"align":1,"folded":false}},"parent_id":"FPELdtBfPoYO8MxuGm2cRZJunDc"},{"block_id":"ZtLIdc02vorVvJxDunfc66Okn7g","block_type":12,"bullet":{"elements":[{"text_run":{"content":"編輯：對已經添加的合并规则可以進行人工編輯。","text_element_style":{"bold":false,"inline_code":false,"italic":false,"strikethrough":false,"underline":false}}}],"style":{"align":1,"folded":false}},"parent_id":"FPELdtBfPoYO8MxuGm2cRZJunDc"},{"block_id":"Hkhod6I0pojqxbx4X22c5pebnpI","block_type":12,"bullet":{"elements":[{"text_run":{"content":"刪除：對已經添加的葛冰规则可以進行刪除。","text_element_style":{"bold":false,"inline_code":false,"italic":false,"strikethrough":false,"underline":false}}}],"style":{"align":1,"folded":false}},"parent_id":"FPELdtBfPoYO8MxuGm2cRZJunDc"},{"block_id":"XxiddYtklo7sapxp7s0cVYvMn0c","block_type":3,"heading1":{"elements":[{"text_run":{"content":"會計分錄","text_element_style":{"bold":false,"inline_code":false,"italic":false,"strikethrough":false,"underline":false}}}],"style":{"align":1,"folded":false}},"parent_id":"FPELdtBfPoYO8MxuGm2cRZJunDc"},{"block_id":"NGg6d12OVo7KBkxbt6TcwKUrnUh","block_type":4,"heading2":{"elements":[{"text_run":{"content":"2.1 適用場景","text_element_style":{"bold":false,"inline_code":false,"italic":false,"strikethrough":false,"underline":false}}}],"style":{"align":1,"folded":false}},"parent_id":"FPELdtBfPoYO8MxuGm2cRZJunDc"},{"block_id":"T2Txd0A55odMIQx7pQSchySlnnb","block_type":2,"parent_id":"FPELdtBfPoYO8MxuGm2cRZJunDc","text":{"elements":[{"text_run":{"content":"使用者在初始化使用會計中台功能時，需要維護的基礎數據","text_element_style":{"bold":false,"inline_code":false,"italic":false,"strikethrough":false,"underline":false}}}],"style":{"align":1,"folded":false}}},{"block_id":"Lt95disbboTUTuxLJlCcxYFhnCf","block_type":4,"heading2":{"elements":[{"text_run":{"content":"2.2 前置條件 ","text_element_style":{"bold":false,"inline_code":false,"italic":false,"strikethrough":false,"underline":false}}}],"style":{"align":1,"folded":false}},"parent_id":"FPELdtBfPoYO8MxuGm2cRZJunDc"},{"block_id":"A9qDdLyImoMTcExWXYcca2a9nJf","block_type":2,"parent_id":"FPELdtBfPoYO8MxuGm2cRZJunDc","text":{"elements":[{"text_run":{"content":"擁有會計中台的菜單權限，並且已經設定了會計工作中涉及的會計科目","text_element_style":{"bold":false,"inline_code":false,"italic":false,"strikethrough":false,"underline":false}}}],"style":{"align":1,"folded":false}}},{"block_id":"JZj9d8sWroglRax2ncHcjt2InHX","block_type":5,"heading3":{"elements":[{"text_run":{"content":"2.2.1 會計分錄列表","text_element_style":{"bold":false,"inline_code":false,"italic":false,"strikethrough":false,"underline":false}}}],"style":{"align":1,"folded":false}},"parent_id":"FPELdtBfPoYO8MxuGm2cRZJunDc"},{"block_id":"E5xKd0TuPoc1aQxwO5hc6sPjnqb","block_type":2,"parent_id":"FPELdtBfPoYO8MxuGm2cRZJunDc","text":{"elements":[{"text_run":{"content":"執行菜單：证券后台>會計中台>會計分錄","text_element_style":{"bold":false,"inline_code":false,"italic":false,"strikethrough":false,"underline":false}}}],"style":{"align":1,"folded":false}}},{"block_id":"VKxud9mUcoiG2Sx6Pm1c9cWjnih","block_type":2,"parent_id":"FPELdtBfPoYO8MxuGm2cRZJunDc","text":{"elements":[{"text_run":{"content":"此功能可以維護會計分錄，其中會計分錄是外部財務系統最重要的會計憑證轉入的依據","text_element_style":{"bold":false,"inline_code":false,"italic":false,"strikethrough":false,"underline":false}}}],"style":{"align":1,"folded":false}}},{"block_id":"V5LkdliZHox9rAxwq9gcixTknQg","block_type":27,"image":{"align":2,"height":634,"token":"QjGrbtZmzo1gxqxPjNTc3Hugn4b","width":1280},"parent_id":"FPELdtBfPoYO8MxuGm2cRZJunDc"},{"block_id":"QhgodFn9ooXqDAxOuiCc0xmBnNe","block_type":2,"parent_id":"FPELdtBfPoYO8MxuGm2cRZJunDc","text":{"elements":[{"text_run":{"content":"首先，系統是支持根據不同數據源配置分錄規則，可以自動地對數據源產生會計分錄，若某些數據源無法自動配置，此功能提供批次導入與手工錄入方式：","text_element_style":{"bold":false,"inline_code":false,"italic":false,"strikethrough":false,"underline":false}}}],"style":{"align":1,"folded":false}}},{"block_id":"H9rsdmLNNoC8CkxBcymcfDfunhc","block_type":2,"parent_id":"FPELdtBfPoYO8MxuGm2cRZJunDc","text":{"elements":[{"text_run":{"content":"如果自動產生分錄後，作業提供新增【編輯】功能，可以修改產生分錄紀錄，同時紀錄新增支付流水新增支票號欄位展示","text_element_style":{"bold":false,"inline_code":false,"italic":false,"strikethrough":false,"underline":false}}}],"style":{"align":1,"folded":false}}},{"block_id":"EsUkdzzPTo3SvJx4gI1cssMpn4q","block_type":27,"image":{"align":2,"height":1412,"token":"CqZlbS8mxo2o2exeVgzc3x28nDb","width":2658},"parent_id":"FPELdtBfPoYO8MxuGm2cRZJunDc"},{"block_id":"HDiGdK5GnoCrDHxOxi3cJCbXnfg","block_type":27,"image":{"align":2,"height":2754,"token":"PFtjbvAAko74FpxyhiHc0oxonPc","width":3270},"parent_id":"FPELdtBfPoYO8MxuGm2cRZJunDc"},{"block_id":"GlAud4U83ocD4sxwq3zcf4pmnrd","block_type":2,"parent_id":"FPELdtBfPoYO8MxuGm2cRZJunDc","text":{"elements":[{"text_run":{"content":"如果需要手工錄入的分錄很少，可以選擇【手動錄入】","text_element_style":{"bold":false,"inline_code":false,"italic":false,"strikethrough":false,"underline":false}}}],"style":{"align":1,"folded":false}}},{"block_id":"G8gOdzPgoofUOCxHaBOcK7c3nJe","block_type":27,"image":{"align":2,"height":1330,"token":"RsZPb9Fn4ofvgfxunhCccLw7nqb","width":2502},"parent_id":"FPELdtBfPoYO8MxuGm2cRZJunDc"},{"block_id":"NcridX2g3oGOc0xsEK9cPNUdnLc","block_type":27,"image":{"align":2,"height":2782,"token":"OAmyb0IQpopXP6xg5U0cMSZcnGb","width":3290},"parent_id":"FPELdtBfPoYO8MxuGm2cRZJunDc"},{"block_id":"Hb1sdeu7xojDvtxIf8vcqNVOnad","block_type":2,"parent_id":"FPELdtBfPoYO8MxuGm2cRZJunDc","text":{"elements":[{"text_run":{"content":"也可以選擇【批量導入】，先行下載範本之後，根據批量範本進行編制分錄並導入到系統中","text_element_style":{"bold":false,"inline_code":false,"italic":false,"strikethrough":false,"underline":false}}}],"style":{"align":1,"folded":false}}},{"block_id":"BP7CdBTMYodR5oxKgRqca9H8nBd","block_type":27,"image":{"align":2,"height":1534,"token":"LFG3bgtVSokpSVx9DNwcWTXfnRb","width":3246},"parent_id":"FPELdtBfPoYO8MxuGm2cRZJunDc"},{"block_id":"X0kFdhdoIo0kkexs3zxchBopnmc","block_type":2,"parent_id":"FPELdtBfPoYO8MxuGm2cRZJunDc","text":{"elements":[{"text_run":{"content":"在記錄右側操作區的【刪除】鍵， 也可進行刪除此會計分錄","text_element_style":{"bold":false,"inline_code":false,"italic":false,"strikethrough":false,"underline":false}}}],"style":{"align":1,"folded":false}}},{"block_id":"Gzojdd7yXo2vgdxaUqYczPcjnid","block_type":27,"image":{"align":2,"height":1474,"token":"LDqxbQHPRo1exKx86CEcZZKunnb","width":3364},"parent_id":"FPELdtBfPoYO8MxuGm2cRZJunDc"},{"block_id":"JXRGdJ9OUotzIjx5ZFbcNvtDnre","block_type":2,"parent_id":"FPELdtBfPoYO8MxuGm2cRZJunDc","text":{"elements":[{"text_run":{"content":"如果某個帳務日期對應的數據源獲取不完整，可以選擇對應日期的數據源進行【重跑】，系統會更新數據源產生最新會計分錄資料","text_element_style":{"bold":false,"inline_code":false,"italic":false,"strikethrough":false,"underline":false}}}],"style":{"align":1,"folded":false}}},{"block_id":"GnHAdyZw8oT2R1xuvLjc6Xfwnoe","block_type":27,"image":{"align":2,"height":1396,"token":"Nv9ibNwYYoHhlNxJlbmc79LZnEd","width":3362},"parent_id":"FPELdtBfPoYO8MxuGm2cRZJunDc"},{"block_id":"WBQwdpXFXorDDBxzONMclcTfnih","block_type":2,"parent_id":"FPELdtBfPoYO8MxuGm2cRZJunDc","text":{"elements":[{"text_run":{"content":"如果系統生成的會計分錄已經核對無誤，手工可以點選【匯總】生成科目餘額匯總表","text_element_style":{"bold":false,"inline_code":false,"italic":false,"strikethrough":false,"underline":false}}}],"style":{"align":1,"folded":false}}},{"block_id":"RF0cdLeqtoiMXlxkmGaclKZwnEg","block_type":27,"image":{"align":2,"height":1452,"token":"RtrJbDpIHo7aA3xk99OcvUplnwb","width":3370},"parent_id":"FPELdtBfPoYO8MxuGm2cRZJunDc"},{"block_id":"Qz1EdkhwXoT1OCx0GihcqQIGnvc","block_type":2,"parent_id":"FPELdtBfPoYO8MxuGm2cRZJunDc","text":{"elements":[{"text_run":{"content":"會計分錄中新增【報表導出】按鈕，方便按照財務軟件格式要求進行報表導出","text_element_style":{"bold":false,"inline_code":false,"italic":false,"strikethrough":false,"underline":false}}}],"style":{"align":1,"folded":false}}},{"block_id":"JuSXdHFhZoya6Fxb9P7cnua5n3e","block_type":27,"image":{"align":2,"height":1606,"token":"FpfgbBv56ouzM3xraQTcXk5unWb","width":3248},"parent_id":"FPELdtBfPoYO8MxuGm2cRZJunDc"},{"block_id":"VYszdUkI3oaMeixhGvfcZUZRnkd","block_type":2,"parent_id":"FPELdtBfPoYO8MxuGm2cRZJunDc","text":{"elements":[{"text_run":{"content":"提供合併會計分錄查詢功能,合併會計分錄時，系統會按賬帳日期獲取匯率","text_element_style":{"bold":false,"inline_code":false,"italic":false,"strikethrough":false,"underline":false}}}],"style":{"align":1,"folded":false}}},{"block_id":"LRBJdEDkToeuDzxGhiccoix1noh","block_type":27,"image":{"align":2,"height":1418,"token":"XYBsbXDA3oylpaxKqLDcrqFknkh","width":3348},"parent_id":"FPELdtBfPoYO8MxuGm2cRZJunDc"},{"block_id":"Sz4PdOsaloo23ExMcVPcSXN8nkh","block_type":3,"children":["WT27d6VCIof3cXxPCd6cyoLWn2e","LamRdLhbuo7zA9xD3KBc0Uionfb","TMnrdQj8gobOOvx9oqucFSN2nad","KhOSduRBKoVqRzxsKdTcZltZnSb","W9X9deKbRozigTx7iEOcrcL4nwb","XepeddGMeoNMsMxcsj5crDkynph","Ki5rd4pfbo4qeWxXYrkcsBKUnnf","Wp40dR4nuomRjWxojXlcKicEnFb","KzXAdvt46onrcoxmjfWcgcMRn1c"],"heading1":{"elements":[{"text_run":{"content":"3.科目餘額","text_element_style":{"bold":false,"inline_code":false,"italic":false,"strikethrough":false,"underline":false}}}],"style":{"align":1,"folded":false}},"parent_id":"FPELdtBfPoYO8MxuGm2cRZJunDc"},{"block_id":"WT27d6VCIof3cXxPCd6cyoLWn2e","block_type":4,"heading2":{"elements":[{"text_run":{"content":"3.1 適用場景","text_element_style":{"bold":false,"inline_code":false,"italic":false,"strikethrough":false,"underline":false}}}],"style":{"align":1,"folded":false}},"parent_id":"Sz4PdOsaloo23ExMcVPcSXN8nkh"},{"block_id":"LamRdLhbuo7zA9xD3KBc0Uionfb","block_type":2,"parent_id":"Sz4PdOsaloo23ExMcVPcSXN8nkh","text":{"elements":[{"text_run":{"content":"根據會計分錄記錄的數據，以科目的形式查看餘額","text_element_style":{"bold":false,"inline_code":false,"italic":false,"strikethrough":false,"underline":false}}}],"style":{"align":1,"folded":false}}},{"block_id":"TMnrdQj8gobOOvx9oqucFSN2nad","block_type":4,"heading2":{"elements":[{"text_run":{"content":"3.2 前置條件 ","text_element_style":{"bold":false,"inline_code":false,"italic":false,"strikethrough":false,"underline":false}}}],"style":{"align":1,"folded":false}},"parent_id":"Sz4PdOsaloo23ExMcVPcSXN8nkh"},{"block_id":"KhOSduRBKoVqRzxsKdTcZltZnSb","block_type":2,"parent_id":"Sz4PdOsaloo23ExMcVPcSXN8nkh","text":{"elements":[{"text_run":{"content":"擁有會計中台的菜單權限，並且會計分錄模組已經存在數據","text_element_style":{"bold":false,"inline_code":false,"italic":false,"strikethrough":false,"underline":false}}}],"style":{"align":1,"folded":false}}},{"block_id":"W9X9deKbRozigTx7iEOcrcL4nwb","block_type":5,"heading3":{"elements":[{"text_run":{"content":"3.3 科目餘額列表","text_element_style":{"bold":false,"inline_code":false,"italic":false,"strikethrough":false,"underline":false}}}],"style":{"align":1,"folded":false}},"parent_id":"Sz4PdOsaloo23ExMcVPcSXN8nkh"},{"block_id":"XepeddGMeoNMsMxcsj5crDkynph","block_type":2,"parent_id":"Sz4PdOsaloo23ExMcVPcSXN8nkh","text":{"elements":[{"text_run":{"content":"執行菜單：會計中台>科目餘額","text_element_style":{"bold":false,"inline_code":false,"italic":false,"strikethrough":false,"underline":false}}}],"style":{"align":1,"folded":false}}},{"block_id":"Ki5rd4pfbo4qeWxXYrkcsBKUnnf","block_type":2,"parent_id":"Sz4PdOsaloo23ExMcVPcSXN8nkh","text":{"elements":[{"text_run":{"content":"系統每日會根據科目明細帳按照帳務日期進行匯總，匯總形成科目餘額匯總表","text_element_style":{"bold":false,"inline_code":false,"italic":false,"strikethrough":false,"underline":false}}}],"style":{"align":1,"folded":false}}},{"block_id":"Wp40dR4nuomRjWxojXlcKicEnFb","block_type":27,"image":{"align":2,"height":1460,"token":"BX20b7Jn9oqKMExiSMkcOL9xnR7","width":3188},"parent_id":"Sz4PdOsaloo23ExMcVPcSXN8nkh"},{"block_id":"KzXAdvt46onrcoxmjfWcgcMRn1c","block_type":3,"children":["FJ3tdDFWKo0VggxuWvIcmHnTnWg","INgJdpFSsotjY8xInTgc1zwLnPb","KxzqdNEYoodZ7jxWWA9cQlkYn2N","VYwedL4ueo0slNxC1JIciFADnae","CVNfdN5cUoaoFUxqIVycB4cXnTh","YfJKd4m3OoGf8nxukXucr4gKnEe","P0JgdjwOCoHy6AxyiwpcSx9VnBf","IrUNdU3kQo8bGSxEifucSHVknpd","D3u5dY3rwoxI9ExgPZhciLrLnHd","Qdy1dLR0Yo4yiIxpmvucXA8Onug","KSl9ddAlzoSAiFx8R9XcAmUnnUg","LSyndGZidoUJHbxkqkQcL1RmnAe"],"heading1":{"elements":[{"text_run":{"content":"4.科目明細帳","text_element_style":{"bold":false,"inline_code":false,"italic":false,"strikethrough":false,"underline":false}}}],"style":{"align":1,"folded":false}},"parent_id":"Sz4PdOsaloo23ExMcVPcSXN8nkh"},{"block_id":"FJ3tdDFWKo0VggxuWvIcmHnTnWg","block_type":4,"heading2":{"elements":[{"text_run":{"content":"4.1 適用場景","text_element_style":{"bold":false,"inline_code":false,"italic":false,"strikethrough":false,"underline":false}}}],"style":{"align":1,"folded":false}},"parent_id":"KzXAdvt46onrcoxmjfWcgcMRn1c"},{"block_id":"INgJdpFSsotjY8xInTgc1zwLnPb","block_type":2,"parent_id":"KzXAdvt46onrcoxmjfWcgcMRn1c","text":{"elements":[{"text_run":{"content":"根據會計分錄記錄的數據，以科目的形式查看餘額","text_element_style":{"bold":false,"inline_code":false,"italic":false,"strikethrough":false,"underline":false}}}],"style":{"align":1,"folded":false}}},{"block_id":"KxzqdNEYoodZ7jxWWA9cQlkYn2N","block_type":4,"heading2":{"elements":[{"text_run":{"content":"4.2 前置條件 ","text_element_style":{"bold":false,"inline_code":false,"italic":false,"strikethrough":false,"underline":false}}}],"style":{"align":1,"folded":false}},"parent_id":"KzXAdvt46onrcoxmjfWcgcMRn1c"},{"block_id":"VYwedL4ueo0slNxC1JIciFADnae","block_type":2,"parent_id":"KzXAdvt46onrcoxmjfWcgcMRn1c","text":{"elements":[{"text_run":{"content":"擁有會計中台的菜單權限，並且會計分錄模組已經存在數據","text_element_style":{"bold":false,"inline_code":false,"italic":false,"strikethrough":false,"underline":false}}}],"style":{"align":1,"folded":false}}},{"block_id":"CVNfdN5cUoaoFUxqIVycB4cXnTh","block_type":4,"heading2":{"elements":[{"text_run":{"content":"4.3 科目明細帳列表","text_element_style":{"bold":false,"inline_code":false,"italic":false,"strikethrough":false,"underline":false}}}],"style":{"align":1,"folded":false}},"parent_id":"KzXAdvt46onrcoxmjfWcgcMRn1c"},{"block_id":"YfJKd4m3OoGf8nxukXucr4gKnEe","block_type":2,"parent_id":"KzXAdvt46onrcoxmjfWcgcMRn1c","text":{"elements":[{"text_run":{"content":"執行菜單：會計中台>會計科目明細帳","text_element_style":{"bold":false,"inline_code":false,"italic":false,"strikethrough":false,"underline":false}}}],"style":{"align":1,"folded":false}}},{"block_id":"P0JgdjwOCoHy6AxyiwpcSx9VnBf","block_type":2,"parent_id":"KzXAdvt46onrcoxmjfWcgcMRn1c","text":{"elements":[{"text_run":{"content":"對於系統按照科目展示的明細帳，可以在此功能進行查詢","text_element_style":{"bold":false,"inline_code":false,"italic":false,"strikethrough":false,"underline":false}}}],"style":{"align":1,"folded":false}}},{"block_id":"IrUNdU3kQo8bGSxEifucSHVknpd","block_type":27,"image":{"align":2,"height":1506,"token":"VToxbKeaXoUOMvxVbylcba2FnAg","width":3218},"parent_id":"KzXAdvt46onrcoxmjfWcgcMRn1c"},{"block_id":"D3u5dY3rwoxI9ExgPZhciLrLnHd","block_type":2,"parent_id":"KzXAdvt46onrcoxmjfWcgcMRn1c","text":{"elements":[{"text_run":{"content":"也可以根據系統生成的科目明細，在此功能可以點選【報表導出】選擇使用對應財務軟體格式導出 ","text_element_style":{"bold":false,"inline_code":false,"italic":false,"strikethrough":false,"underline":false}}}],"style":{"align":1,"folded":false}}},{"block_id":"Qdy1dLR0Yo4yiIxpmvucXA8Onug","block_type":2,"children":["WFOwdWduUoO7daxQNBYcLCcFnLh","TusNdh2enoDbGTxMS0HcFkXQnUh","Fbb3dtsQeoez7CxWMPkcdLBMnMg","BvV4d1AqDoM5j0x6DZvc4tAJnKf","Ib0gdV96doEKcsxkbo9cvpQ2nFd"],"parent_id":"KzXAdvt46onrcoxmjfWcgcMRn1c","text":{"elements":[{"text_run":{"content":"目前系統支持以下GL 軟體匯入格式：","text_element_style":{"bold":false,"inline_code":false,"italic":false,"strikethrough":false,"underline":false}}}],"style":{"align":1,"folded":false,"indentation_level":"NoIndent"}}},{"block_id":"WFOwdWduUoO7daxQNBYcLCcFnLh","block_type":12,"bullet":{"elements":[{"text_run":{"content":"FlexSystem ","text_element_style":{"bold":false,"inline_code":false,"italic":false,"strikethrough":false,"underline":false}}}],"style":{"align":1,"folded":false}},"parent_id":"Qdy1dLR0Yo4yiIxpmvucXA8Onug"},{"block_id":"TusNdh2enoDbGTxMS0HcFkXQnUh","block_type":12,"bullet":{"elements":[{"text_run":{"content":"GeneralLedgerSystem","text_element_style":{"bold":false,"inline_code":false,"italic":false,"strikethrough":false,"underline":false}}}],"style":{"align":1,"folded":false}},"parent_id":"Qdy1dLR0Yo4yiIxpmvucXA8Onug"},{"block_id":"Fbb3dtsQeoez7CxWMPkcdLBMnMg","block_type":12,"bullet":{"elements":[{"text_run":{"content":"SunSystem","text_element_style":{"bold":false,"inline_code":false,"italic":false,"strikethrough":false,"underline":false}}}],"style":{"align":1,"folded":false}},"parent_id":"Qdy1dLR0Yo4yiIxpmvucXA8Onug"},{"block_id":"BvV4d1AqDoM5j0x6DZvc4tAJnKf","block_type":12,"bullet":{"elements":[{"text_run":{"content":"Yonyou 用友","text_element_style":{"bold":false,"inline_code":false,"italic":false,"strikethrough":false,"underline":false}}}],"style":{"align":1,"folded":false}},"parent_id":"Qdy1dLR0Yo4yiIxpmvucXA8Onug"},{"block_id":"Ib0gdV96doEKcsxkbo9cvpQ2nFd","block_type":12,"bullet":{"elements":[{"text_run":{"content":"FlexAccount V11","text_element_style":{"bold":false,"inline_code":false,"italic":false,"strikethrough":false,"underline":false}}}],"style":{"align":1,"folded":false}},"parent_id":"Qdy1dLR0Yo4yiIxpmvucXA8Onug"},{"block_id":"KSl9ddAlzoSAiFx8R9XcAmUnnUg","block_type":27,"image":{"align":2,"height":1622,"token":"YgEJbAWadoKj7dxd3Hlc6XEcntr","width":3256},"parent_id":"KzXAdvt46onrcoxmjfWcgcMRn1c"},{"block_id":"LSyndGZidoUJHbxkqkQcL1RmnAe","block_type":2,"parent_id":"KzXAdvt46onrcoxmjfWcgcMRn1c","text":{"elements":[{"text_run":{"content":"","text_element_style":{"bold":false,"inline_code":false,"italic":false,"strikethrough":false,"underline":false}}}],"style":{"align":1,"folded":false}}},{"block_id":"VoiddVa5Moob1wxn1UAcEachnVc","block_type":3,"children":["TYmSdLzB4oXTbOxA3GEcooQxnQc","IutRdtGTcosC6wxhZL9cUdpznce","QEYPdh71xoiYdJxeFhcc3u1mnEg","WSimdUMe3oKDMrxZUhZc0GNTnyh","WClWd7AR6osJwBxvW1Lcd8hQnUb","U1QddCujKosVivxCRWGcozjgnOc","EFGvdfST6owAkwx1lqHcAICPnlc","EiUPdpdMloDRYWxlp61cuTMUnZC","G4sDdylnrod1pjxZ3oLcFsVMnne","DdzSdVKiUog7mFxqwy4cI8WfnWd","GfSPd89S5oavQ2xNXKlcH762nrd","RVhedktAuoVJ6GxXBbYciBlDnvh","MiChdsCpVoR9fux2BWvccOF6nCh","VT7YdyxhzoTxrPxWBC0clllonLe","AVo8dyCKcoKjddxAz9TcjFtXnCY","NDvUdFcmdoPMP1xR5LFcnN0Dn1f","J6MtdQc0QoHs9AxmnTmcFmUynJg","S0CMdiaIXogkbUx7Epfcw6t3nIe","P6Rpd3j08oWnPcx3JqKcuweYnud","MbwZdrdWmozHjYxexXVcwF0fnxd"],"heading1":{"elements":[{"text_run":{"content":"5.銀行餘額","text_element_style":{"bold":false,"inline_code":false,"italic":false,"strikethrough":false,"underline":false}}}],"style":{"align":1,"folded":false}},"parent_id":"FPELdtBfPoYO8MxuGm2cRZJunDc"},{"block_id":"TYmSdLzB4oXTbOxA3GEcooQxnQc","block_type":4,"heading2":{"elements":[{"text_run":{"content":"5.1 適用場景 ","text_element_style":{"bold":false,"inline_code":false,"italic":false,"strikethrough":false,"underline":false}}}],"style":{"align":1,"folded":false}},"parent_id":"VoiddVa5Moob1wxn1UAcEachnVc"},{"block_id":"IutRdtGTcosC6wxhZL9cUdpznce","block_type":2,"parent_id":"VoiddVa5Moob1wxn1UAcEachnVc","text":{"elements":[{"text_run":{"content":"使用者需要根據銀行提供的流水與系統存在的自己資料進行多維度比對","text_element_style":{"bold":false,"inline_code":false,"italic":false,"strikethrough":false,"underline":false}}}],"style":{"align":1,"folded":false}}},{"block_id":"QEYPdh71xoiYdJxeFhcc3u1mnEg","block_type":4,"heading2":{"elements":[{"text_run":{"content":"5.2 前置條件 ","text_element_style":{"bold":false,"inline_code":false,"italic":false,"strikethrough":false,"underline":false}}}],"style":{"align":1,"folded":false}},"parent_id":"VoiddVa5Moob1wxn1UAcEachnVc"},{"block_id":"WSimdUMe3oKDMrxZUhZc0GNTnyh","block_type":2,"parent_id":"VoiddVa5Moob1wxn1UAcEachnVc","text":{"elements":[{"text_run":{"content":"銀行流水與後台資料均已生成","text_element_style":{"bold":false,"inline_code":false,"italic":false,"strikethrough":false,"underline":false}}}],"style":{"align":1,"folded":false}}},{"block_id":"WClWd7AR6osJwBxvW1Lcd8hQnUb","block_type":4,"heading2":{"elements":[{"text_run":{"content":"5.3 维度展示","text_element_style":{"bold":false,"inline_code":false,"italic":false,"strikethrough":false,"underline":false}}}],"style":{"align":1,"folded":false}},"parent_id":"VoiddVa5Moob1wxn1UAcEachnVc"},{"block_id":"U1QddCujKosVivxCRWGcozjgnOc","block_type":5,"heading3":{"elements":[{"text_run":{"content":"5.3.1 帳單核對","text_element_style":{"bold":false,"inline_code":false,"italic":false,"strikethrough":false,"underline":false}}}],"style":{"align":1,"folded":false}},"parent_id":"VoiddVa5Moob1wxn1UAcEachnVc"},{"block_id":"EFGvdfST6owAkwx1lqHcAICPnlc","block_type":2,"parent_id":"VoiddVa5Moob1wxn1UAcEachnVc","text":{"elements":[{"text_run":{"content":"執行菜單：會計中台>銀行餘額>帳單核對 Tab 頁籤","text_element_style":{"bold":false,"inline_code":false,"italic":false,"strikethrough":false,"underline":false}}}],"style":{"align":1,"folded":false}}},{"block_id":"EiUPdpdMloDRYWxlp61cuTMUnZC","block_type":2,"parent_id":"VoiddVa5Moob1wxn1UAcEachnVc","text":{"elements":[{"text_run":{"content":"根據銀行賬單歷史發生額計算的結果與銀行歷史餘額進行核對，進而保證銀行賬單明細的準確性和完整性。","text_element_style":{"bold":false,"inline_code":false,"italic":false,"strikethrough":false,"underline":false}}}],"style":{"align":1,"folded":false}}},{"block_id":"G4sDdylnrod1pjxZ3oLcFsVMnne","block_type":27,"image":{"align":2,"height":1542,"token":"Ysmcb23N5o3BHdxy6bpcittRnDf","width":3234},"parent_id":"VoiddVa5Moob1wxn1UAcEachnVc"},{"block_id":"DdzSdVKiUog7mFxqwy4cI8WfnWd","block_type":5,"heading3":{"elements":[{"text_run":{"content":"5.3.2 歷史餘額","text_element_style":{"bold":false,"inline_code":false,"italic":false,"strikethrough":false,"underline":false}}}],"style":{"align":1,"folded":false}},"parent_id":"VoiddVa5Moob1wxn1UAcEachnVc"},{"block_id":"GfSPd89S5oavQ2xNXKlcH762nrd","block_type":2,"parent_id":"VoiddVa5Moob1wxn1UAcEachnVc","text":{"elements":[{"text_run":{"content":"執行菜單：會計中台>銀行餘額>歷史餘額 Tab 頁籤","text_element_style":{"bold":false,"inline_code":false,"italic":false,"strikethrough":false,"underline":false}}}],"style":{"align":1,"folded":false}}},{"block_id":"RVhedktAuoVJ6GxXBbYciBlDnvh","block_type":2,"parent_id":"VoiddVa5Moob1wxn1UAcEachnVc","text":{"elements":[{"text_run":{"content":"是指券商公司所有銀行帳戶某一帳務日期的銀行實際餘額。","text_element_style":{"bold":false,"inline_code":false,"italic":false,"strikethrough":false,"underline":false}}}],"style":{"align":1,"folded":false}}},{"block_id":"MiChdsCpVoR9fux2BWvccOF6nCh","block_type":2,"parent_id":"VoiddVa5Moob1wxn1UAcEachnVc","text":{"elements":[{"text_run":{"content":"可以選擇批次導入","text_element_style":{"bold":false,"inline_code":false,"italic":false,"strikethrough":false,"underline":false}}}],"style":{"align":1,"folded":false}}},{"block_id":"VT7YdyxhzoTxrPxWBC0clllonLe","block_type":27,"image":{"align":2,"height":1524,"token":"Of7bbY2vQoNEOcx0xD7cmmIknrc","width":3238},"parent_id":"VoiddVa5Moob1wxn1UAcEachnVc"},{"block_id":"AVo8dyCKcoKjddxAz9TcjFtXnCY","block_type":27,"image":{"align":2,"height":1234,"token":"GxMrbVNrJoiHrpxrk6cc5WCgnrd","width":3242},"parent_id":"VoiddVa5Moob1wxn1UAcEachnVc"},{"block_id":"NDvUdFcmdoPMP1xR5LFcnN0Dn1f","block_type":5,"heading3":{"elements":[{"text_run":{"content":"5.3.3 實時餘額","text_element_style":{"bold":false,"inline_code":false,"italic":false,"strikethrough":false,"underline":false}}}],"style":{"align":1,"folded":false}},"parent_id":"VoiddVa5Moob1wxn1UAcEachnVc"},{"block_id":"J6MtdQc0QoHs9AxmnTmcFmUynJg","block_type":2,"parent_id":"VoiddVa5Moob1wxn1UAcEachnVc","text":{"elements":[{"text_run":{"content":"執行菜單：會計中台>銀行餘額>實時餘額 Tab 頁籤","text_element_style":{"bold":false,"inline_code":false,"italic":false,"strikethrough":false,"underline":false}}}],"style":{"align":1,"folded":false}}},{"block_id":"S0CMdiaIXogkbUx7Epfcw6t3nIe","block_type":2,"parent_id":"VoiddVa5Moob1wxn1UAcEachnVc","text":{"elements":[{"text_run":{"content":"是指券商公司已對接 API 的銀行賬戶的銀行實時餘額。","text_element_style":{"bold":false,"inline_code":false,"italic":false,"strikethrough":false,"underline":false}}}],"style":{"align":1,"folded":false}}},{"block_id":"P6Rpd3j08oWnPcx3JqKcuweYnud","block_type":27,"image":{"align":2,"height":1242,"token":"LTfmbPEYtoFzbcxzZ8LcTJitn3c","width":3252},"parent_id":"VoiddVa5Moob1wxn1UAcEachnVc"},{"block_id":"MbwZdrdWmozHjYxexXVcwF0fnxd","block_type":2,"parent_id":"VoiddVa5Moob1wxn1UAcEachnVc","text":{"elements":[{"text_run":{"content":"","text_element_style":{"bold":false,"inline_code":false,"italic":false,"strikethrough":false,"underline":false}}}],"style":{"align":1,"folded":false}}},{"block_id":"JkzsdhDEqoczX0xORCWcUnKbncZ","block_type":3,"children":["Q5zIdoLChoin5fxkHUocEuRGnUg","KpWEdhRlSocmuax9H24cj20rn2b","EMTHdeXP7oSzFYxwEB0c5wgKncb","JnLsdFHdho6irgxOhXicoLf7nlf","MQRQd6hpVov3IixbTgLcTAADnyc","Er6Udxx6Yoe4WTxkLX2cfOzLn6d","Kn3FdAaa6ojiTzx1CuCch0AKnKh","GxqGd1xALo9qIuxsPbkctxBLnjb","R7pGdPhBkoVwY5xRtmWc4u0DnGg","UBV3dzzdZoeDvvxUSNtcUJPZnjg","T8SAdQfTPoHMTmxIz9HcPNe7nQe","X3ThdFPd7oOl2LxZCWLcflBAnNg","MlAodX0T1o5rJNxLMrzcsfIance","OSyhdFnymotwuHx9sNVcwWuOnff","FGYXdt0yOoppDTxExe0cyRcqnjd","Io5EdXhzfoI99KxiVPccg7rznCd","Eh14ds9y6o444txMCc2cNvScnZc","R8McdWz0XoFwZHx7ovRcbPwNnYe","CtDhdyJMBorsEJxuNt7cTUJwnEE","UMgwdin5RoqcxZxrrWBc7qh9n8g","Csz9dXIl2od8DmxrFVucHg1AnZd","OmsldFxHmo68nYxvUFPcjeSon88","W8Cgdi0OloiM3uxZR07cGXoyneg","SenDdccMSop8PqxNQLsctekMnOd","Q3QSdQHrloVCLYxrjQjcHl5DnMc","E7sZdeVj9ogvLBxEV0hc2mBBnrg","ZofSdr49Soya1AxhgEAcIXjWnlf","NIR9dz3icoDBnDxafNFcdPYHnYg","DTHKdJjsXo4hD3x7z4RcfBQRnio","PnnwducFlo589DxclUKcheUrn1f","KI25dxaH0oDBgtxkrpkcm6gBnyK"],"heading1":{"elements":[{"text_run":{"content":"6.記帳數據源","text_element_style":{"bold":false,"inline_code":false,"italic":false,"strikethrough":false,"underline":false}}}],"style":{"align":1,"folded":false}},"parent_id":"FPELdtBfPoYO8MxuGm2cRZJunDc"},{"block_id":"Q5zIdoLChoin5fxkHUocEuRGnUg","block_type":4,"heading2":{"elements":[{"text_run":{"content":"6.1 適用場景 ","text_element_style":{"bold":false,"inline_code":false,"italic":false,"strikethrough":false,"underline":false}}}],"style":{"align":1,"folded":false}},"parent_id":"JkzsdhDEqoczX0xORCWcUnKbncZ"},{"block_id":"KpWEdhRlSocmuax9H24cj20rn2b","block_type":2,"parent_id":"JkzsdhDEqoczX0xORCWcUnKbncZ","text":{"elements":[{"text_run":{"content":"用戶在記帳時需依照各類明細會計資料進行分類整理，並根據整理出的異常資料進行單獨處理","text_element_style":{"bold":false,"inline_code":false,"italic":false,"strikethrough":false,"underline":false}}}],"style":{"align":1,"folded":false}}},{"block_id":"EMTHdeXP7oSzFYxwEB0c5wgKncb","block_type":4,"heading2":{"elements":[{"text_run":{"content":"6.2 前置條件 ","text_element_style":{"bold":false,"inline_code":false,"italic":false,"strikethrough":false,"underline":false}}}],"style":{"align":1,"folded":false}},"parent_id":"JkzsdhDEqoczX0xORCWcUnKbncZ"},{"block_id":"JnLsdFHdho6irgxOhXicoLf7nlf","block_type":2,"parent_id":"JkzsdhDEqoczX0xORCWcUnKbncZ","text":{"elements":[{"text_run":{"content":"銀行流水、CCASS 資料等均已準備就緒","text_element_style":{"bold":false,"inline_code":false,"italic":false,"strikethrough":false,"underline":false}}}],"style":{"align":1,"folded":false}}},{"block_id":"MQRQd6hpVov3IixbTgLcTAADnyc","block_type":5,"heading3":{"elements":[{"text_run":{"content":"6.3 異常數據源","text_element_style":{"bold":false,"inline_code":false,"italic":false,"strikethrough":false,"underline":false}}}],"style":{"align":1,"folded":false}},"parent_id":"JkzsdhDEqoczX0xORCWcUnKbncZ"},{"block_id":"Er6Udxx6Yoe4WTxkLX2cfOzLn6d","block_type":2,"parent_id":"JkzsdhDEqoczX0xORCWcUnKbncZ","text":{"elements":[{"text_run":{"content":"執行菜單：會計中台>記帳數據源>異常數據源 Tab 頁籤","text_element_style":{"bold":false,"inline_code":false,"italic":false,"strikethrough":false,"underline":false}}}],"style":{"align":1,"folded":false}}},{"block_id":"Kn3FdAaa6ojiTzx1CuCch0AKnKh","block_type":12,"bullet":{"elements":[{"text_run":{"content":"系統對於無法自動形成分錄的數據源會視作為異常數據，可以在此功能進行查詢","text_element_style":{"bold":false,"inline_code":false,"italic":false,"strikethrough":false,"underline":false}}}],"style":{"align":1,"folded":false}},"parent_id":"JkzsdhDEqoczX0xORCWcUnKbncZ"},{"block_id":"GxqGd1xALo9qIuxsPbkctxBLnjb","block_type":27,"image":{"align":2,"height":1576,"token":"ASwGbCAVgoHlNlxKc17coIgInme","width":3240},"parent_id":"JkzsdhDEqoczX0xORCWcUnKbncZ"},{"block_id":"R7pGdPhBkoVwY5xRtmWc4u0DnGg","block_type":12,"bullet":{"elements":[{"text_run":{"content":"對於異常數據源，可以在記錄列表通過點擊「異常數據源單號」，可以跳轉到具體數據源","text_element_style":{"bold":false,"inline_code":false,"italic":false,"strikethrough":false,"underline":false}}}],"style":{"align":1,"folded":false}},"parent_id":"JkzsdhDEqoczX0xORCWcUnKbncZ"},{"block_id":"UBV3dzzdZoeDvvxUSNtcUJPZnjg","block_type":27,"image":{"align":2,"height":1408,"token":"Pr9UbXL2moXpbdxghVEc90r0nre","width":3240},"parent_id":"JkzsdhDEqoczX0xORCWcUnKbncZ"},{"block_id":"T8SAdQfTPoHMTmxIz9HcPNe7nQe","block_type":5,"heading3":{"elements":[{"text_run":{"content":"6.4 客戶收費帳單","text_element_style":{"bold":false,"inline_code":false,"italic":false,"strikethrough":false,"underline":false}}}],"style":{"align":1,"folded":false}},"parent_id":"JkzsdhDEqoczX0xORCWcUnKbncZ"},{"block_id":"X3ThdFPd7oOl2LxZCWLcflBAnNg","block_type":2,"parent_id":"JkzsdhDEqoczX0xORCWcUnKbncZ","text":{"elements":[{"text_run":{"content":"執行菜單：會計中台>記帳數據源>客戶收費帳單 Tab 頁籤","text_element_style":{"bold":false,"inline_code":false,"italic":false,"strikethrough":false,"underline":false}}}],"style":{"align":1,"folded":false}}},{"block_id":"MlAodX0T1o5rJNxLMrzcsfIance","block_type":12,"bullet":{"elements":[{"text_run":{"content":"由於支付流水中用戶發生的各種交易費用，比如股票交易是匯總數，類似於佣金、平台費和各種第三方收費合計，無法滿足財務入帳需求，需要解析用戶交易收費明細，作為會計記賬的數據源。","text_element_style":{"bold":false,"inline_code":false,"italic":false,"strikethrough":false,"underline":false}}}],"style":{"align":1,"folded":false}},"parent_id":"JkzsdhDEqoczX0xORCWcUnKbncZ"},{"block_id":"OSyhdFnymotwuHx9sNVcwWuOnff","block_type":12,"bullet":{"elements":[{"text_run":{"content":"客戶收費帳單對於股票交易類型可以更細分配置，可以支持單獨區分出暗盤，並且暗盤交易可以單獨配置分錄規則並形成會計分錄","text_element_style":{"bold":false,"inline_code":false,"italic":false,"strikethrough":false,"underline":false}}}],"style":{"align":1,"folded":false}},"parent_id":"JkzsdhDEqoczX0xORCWcUnKbncZ"},{"block_id":"FGYXdt0yOoppDTxExe0cyRcqnjd","block_type":12,"bullet":{"elements":[{"text_run":{"content":"記帳數據源“客戶收費帳單”增加【帳務日期】，並用於記帳分錄帳務日期取值","text_element_style":{"bold":false,"inline_code":false,"italic":false,"strikethrough":false,"underline":false}}}],"style":{"align":1,"folded":false}},"parent_id":"JkzsdhDEqoczX0xORCWcUnKbncZ"},{"block_id":"Io5EdXhzfoI99KxiVPccg7rznCd","block_type":27,"image":{"align":2,"height":1502,"token":"Km53bLm0RoJ0pcx6HM1c0BfEn1e","width":3206},"parent_id":"JkzsdhDEqoczX0xORCWcUnKbncZ"},{"block_id":"Eh14ds9y6o444txMCc2cNvScnZc","block_type":5,"heading3":{"elements":[{"text_run":{"content":"6.5 支付流水","text_element_style":{"bold":false,"inline_code":false,"italic":false,"strikethrough":false,"underline":false}}}],"style":{"align":1,"folded":false}},"parent_id":"JkzsdhDEqoczX0xORCWcUnKbncZ"},{"block_id":"R8McdWz0XoFwZHx7ovRcbPwNnYe","block_type":2,"parent_id":"JkzsdhDEqoczX0xORCWcUnKbncZ","text":{"elements":[{"text_run":{"content":"執行菜單：會計中台>記帳數據源>支付流水 Tab 頁籤","text_element_style":{"bold":false,"inline_code":false,"italic":false,"strikethrough":false,"underline":false}}}],"style":{"align":1,"folded":false}}},{"block_id":"CtDhdyJMBorsEJxuNt7cTUJwnEE","block_type":12,"bullet":{"elements":[{"text_run":{"content":"是指券商公司記錄用戶交易變動明細表，會計中台根據轉賬、出賬和入賬進行規範獲取，作為會計分錄中信息流記賬的數據。","text_element_style":{"bold":false,"inline_code":false,"italic":false,"strikethrough":false,"underline":false}}}],"style":{"align":1,"folded":false}},"parent_id":"JkzsdhDEqoczX0xORCWcUnKbncZ"},{"block_id":"UMgwdin5RoqcxZxrrWBc7qh9n8g","block_type":27,"image":{"align":2,"height":1502,"token":"WcpZbfvvyoL8JwxccTicujfsnJd","width":3230},"parent_id":"JkzsdhDEqoczX0xORCWcUnKbncZ"},{"block_id":"Csz9dXIl2od8DmxrFVucHg1AnZd","block_type":2,"parent_id":"JkzsdhDEqoczX0xORCWcUnKbncZ","text":{"elements":[{"text_run":{"content":"","text_element_style":{"bold":false,"inline_code":false,"italic":false,"strikethrough":false,"underline":false}}}],"style":{"align":1,"folded":false}}},{"block_id":"OmsldFxHmo68nYxvUFPcjeSon88","block_type":5,"heading3":{"elements":[{"text_run":{"content":"6.6 CCASS 賬單","text_element_style":{"bold":false,"inline_code":false,"italic":false,"strikethrough":false,"underline":false}}}],"style":{"align":1,"folded":false}},"parent_id":"JkzsdhDEqoczX0xORCWcUnKbncZ"},{"block_id":"W8Cgdi0OloiM3uxZR07cGXoyneg","block_type":2,"parent_id":"JkzsdhDEqoczX0xORCWcUnKbncZ","text":{"elements":[{"text_run":{"content":"執行菜單：會計中台>記帳數據源>CCASS 賬單Tab 頁籤","text_element_style":{"bold":false,"inline_code":false,"italic":false,"strikethrough":false,"underline":false}}}],"style":{"align":1,"folded":false}}},{"block_id":"SenDdccMSop8PqxNQLsctekMnOd","block_type":12,"bullet":{"elements":[{"text_run":{"content":"增加 CCASS 文件解析，此 CCASS 數據源是相關文件導入後，系統自動根據配置完成會計分錄處理，可在此 Tab 查詢記錄或刪除已轉入的數據源分錄","text_element_style":{"bold":false,"inline_code":false,"italic":false,"strikethrough":false,"underline":false}}}],"style":{"align":1,"folded":false}},"parent_id":"JkzsdhDEqoczX0xORCWcUnKbncZ"},{"block_id":"Q3QSdQHrloVCLYxrjQjcHl5DnMc","block_type":27,"image":{"align":2,"height":1478,"token":"NAoebDTf7oGM62xJCQJcuzWEnag","width":3240},"parent_id":"JkzsdhDEqoczX0xORCWcUnKbncZ"},{"block_id":"E7sZdeVj9ogvLBxEV0hc2mBBnrg","block_type":2,"parent_id":"JkzsdhDEqoczX0xORCWcUnKbncZ","text":{"elements":[{"text_run":{"content":"","text_element_style":{"bold":false,"inline_code":false,"italic":false,"strikethrough":false,"underline":false}}}],"style":{"align":1,"folded":false}}},{"block_id":"ZofSdr49Soya1AxhgEAcIXjWnlf","block_type":5,"heading3":{"elements":[{"text_run":{"content":"6.7 新股帳單","text_element_style":{"bold":false,"inline_code":false,"italic":false,"strikethrough":false,"underline":false}}}],"style":{"align":1,"folded":false}},"parent_id":"JkzsdhDEqoczX0xORCWcUnKbncZ"},{"block_id":"NIR9dz3icoDBnDxafNFcdPYHnYg","block_type":2,"parent_id":"JkzsdhDEqoczX0xORCWcUnKbncZ","text":{"elements":[{"text_run":{"content":"執行菜單：會計中台>記帳數據源>新股帳單Tab 頁籤","text_element_style":{"bold":false,"inline_code":false,"italic":false,"strikethrough":false,"underline":false}}}],"style":{"align":1,"folded":false}}},{"block_id":"DTHKdJjsXo4hD3x7z4RcfBQRnio","block_type":12,"bullet":{"elements":[{"text_run":{"content":"新增新股帳單","text_element_style":{"bold":false,"inline_code":false,"italic":false,"strikethrough":false,"underline":false}}}],"style":{"align":1,"folded":false}},"parent_id":"JkzsdhDEqoczX0xORCWcUnKbncZ"},{"block_id":"PnnwducFlo589DxclUKcheUrn1f","block_type":27,"image":{"align":2,"height":1120,"token":"MwFQbP7x5oN11RxzIeGcYJwCnXf","width":3262},"parent_id":"JkzsdhDEqoczX0xORCWcUnKbncZ"},{"block_id":"KI25dxaH0oDBgtxkrpkcm6gBnyK","block_type":3,"children":["PbHmdQLxyoTYPixSSBzcbtudnEd","PXSsd2wGhokJzWxfEH2cqvtNnKf","DHJidsehYoe3MFxEglpcQG1xn9f","BUtadv6Y5oM0EOxJkF9cFEjWnRb","Ijbddn01eodqTYxKinXcuQtxndd","JQQLd27Hio7y2cxltfacymbjnOf","BqtndjWCxordLwxmyNmc6LRDn2b","Do05dYA1uo71IQxJKpAcDTnOn1e"],"heading1":{"elements":[{"text_run":{"content":"7.入金在途明細","text_element_style":{"bold":false,"inline_code":false,"italic":false,"strikethrough":false,"underline":false}}}],"style":{"align":1,"folded":false}},"parent_id":"JkzsdhDEqoczX0xORCWcUnKbncZ"},{"block_id":"PbHmdQLxyoTYPixSSBzcbtudnEd","block_type":4,"heading2":{"elements":[{"text_run":{"content":"7.1 適用場景 ","text_element_style":{"bold":false,"inline_code":false,"italic":false,"strikethrough":false,"underline":false}}}],"style":{"align":1,"folded":false}},"parent_id":"KI25dxaH0oDBgtxkrpkcm6gBnyK"},{"block_id":"PXSsd2wGhokJzWxfEH2cqvtNnKf","block_type":2,"parent_id":"KI25dxaH0oDBgtxkrpkcm6gBnyK","text":{"elements":[{"text_run":{"content":"作為追蹤客戶在入金未完成狀態時的記錄參考","text_element_style":{"bold":false,"inline_code":false,"italic":false,"strikethrough":false,"underline":false}}}],"style":{"align":1,"folded":false}}},{"block_id":"DHJidsehYoe3MFxEglpcQG1xn9f","block_type":4,"heading2":{"elements":[{"text_run":{"content":"7.2 前置條件 ","text_element_style":{"bold":false,"inline_code":false,"italic":false,"strikethrough":false,"underline":false}}}],"style":{"align":1,"folded":false}},"parent_id":"KI25dxaH0oDBgtxkrpkcm6gBnyK"},{"block_id":"BUtadv6Y5oM0EOxJkF9cFEjWnRb","block_type":2,"parent_id":"KI25dxaH0oDBgtxkrpkcm6gBnyK","text":{"elements":[{"text_run":{"content":"入金流程未完成","text_element_style":{"bold":false,"inline_code":false,"italic":false,"strikethrough":false,"underline":false}}}],"style":{"align":1,"folded":false}}},{"block_id":"Ijbddn01eodqTYxKinXcuQtxndd","block_type":2,"parent_id":"KI25dxaH0oDBgtxkrpkcm6gBnyK","text":{"elements":[{"text_run":{"content":"執行菜單：會計中台>入金在途明細","text_element_style":{"bold":false,"inline_code":false,"italic":false,"strikethrough":false,"underline":false}}}],"style":{"align":1,"folded":false}}},{"block_id":"JQQLd27Hio7y2cxltfacymbjnOf","block_type":12,"bullet":{"elements":[{"text_run":{"content":"提供在途資金的匯總記錄查詢","text_element_style":{"bold":false,"inline_code":false,"italic":false,"strikethrough":false,"underline":false}}}],"style":{"align":1,"folded":false}},"parent_id":"KI25dxaH0oDBgtxkrpkcm6gBnyK"},{"block_id":"BqtndjWCxordLwxmyNmc6LRDn2b","block_type":27,"image":{"align":2,"height":1530,"token":"Axt7bzD5wocGozxjeUlcflaonkc","width":3309},"parent_id":"KI25dxaH0oDBgtxkrpkcm6gBnyK"},{"block_id":"Do05dYA1uo71IQxJKpAcDTnOn1e","block_type":2,"parent_id":"KI25dxaH0oDBgtxkrpkcm6gBnyK","text":{"elements":[{"text_run":{"content":"","text_element_style":{"bold":false,"inline_code":false,"italic":false,"strikethrough":false,"underline":false}}}],"style":{"align":1,"folded":false}}}]}