{"obj_edit_time":"1709186354","blocks":[{"block_id":"L4s3d5sqqoP99gxwjCUc4AZZnRh","block_type":1,"children":["IaGJdIjPkovj1RxfvHCcu0uHnzd","OXqldf7k0oWWb8xWAG0cnEaOng4","PkfEd1jrRotfpyxKZ1ccTdR4ncc","SpW4drN0EobodfxSXtkcQ3x4nfe","VF04dDS4yokytDxZiYFcBBTenBf","AUASd9CY6ohLEQxixhVcYVafnXc","DyDgd701toh4Bqx33jucAW71nSb","GJcndN1yOo1Zrjx6jlRcCUZbnBc","IcLudf8gMoS0oQxMU66coVfLnmc","X3LhdGYesojcklxux7xcOjZln8c","Uni6dxUrHodJYMxNbafc19dlnNe","EaYhdtgRAoUL9Ex2PsBcbYfInRf","PJhzdM6NloQTtxx9MWtcy8m0nUg","SH9ydf0lqoDA4Ix7c7icwBFhnug","ATh7daaiIofwoQxrnnocmNlLn7g","PTzadtBEvojqXrxMfXCchaT1nrh","QwfvdRv7toHaFMxG5dhc86jYnPe","CHj5dv9yco18aSxzpSJcMaOknyS","ReKmdnCtuoKcG6xHzb4cKcvvnvc","Tt8UdPUvTop900xlVKkcwh90nMe","SYCYdOQodo3FMrx3UoKcUg7xnAf","EaMHdfU3hoLmw3xksIzcYoHjnKg","Q8OsdwyMvoWszex05DucgVvZnqh","VFImduDLtoP7ipxg1ifcriMKnXb","HSNZdadaAoMXlbx11hOczY8gnkb","HxU1doRqAoG0qAx4BLNcu4bGnzc","SleJdvwagoJei5xNCeacRvnJnHh","BHoHdi7UKoHLLlxx70zcjynGnEf","SMLAdOk6LoOAyoxwg4YclgM3nue","RFfIdaFAPoe0f0xmkwMcPnBtn5f","EtvvdPxxNoveQhx7okac6QAjnbz","X1s2dhVwuoCulrxWaQFcfkVfnvg","GcSMd30Uko1EW2xTOaDcgvgpnUb","ONWRdpfmMoYGWrxplxac4gIzngf","X03DdPITXosfiAxCzaAckZGDn9f","YppIdGevso8j3dxTdITcfLHKn9d","E8Grdjj8KoAFTyxCjTicBHcSnYe","UyZVdtnRCoJnwBxOz7RcEyQXnwK","L9ANd5YPxokN60xbv4IcP6jgn8f","R0q5diP7JonlUtxrYUHcBMK1n9R","I3gfdVoEBoUEmmxjXWWc6JHznZf","Nn1Cd4pa4oYkFRxjbYRcKqUZnAc","AYZQdEasxo2BSWxFeuKc46annmb","NuKFdbC4oo8wKAxTVcGckUymnug","Nd52dwmjhomX8fxXP63cBdk0nuf","SOt3dCY5HoebwnxahpZcxtk7n2b","HnahdF66zorG3Xx872FcDhfDn7V","TERFdqSHuot6otxYmRGcMnBDnkg"],"page":{"elements":[{"text_run":{"content":"系統介紹","text_element_style":{"bold":false,"inline_code":false,"italic":false,"strikethrough":false,"underline":false}}}],"style":{"align":1}},"parent_id":""},{"block_id":"IaGJdIjPkovj1RxfvHCcu0uHnzd","block_type":3,"heading1":{"elements":[{"text_run":{"content":"一、系統介紹","text_element_style":{"bold":false,"inline_code":false,"italic":false,"strikethrough":false,"underline":false}}}],"style":{"align":1,"folded":false}},"parent_id":"L4s3d5sqqoP99gxwjCUc4AZZnRh"},{"block_id":"OXqldf7k0oWWb8xWAG0cnEaOng4","block_type":2,"parent_id":"L4s3d5sqqoP99gxwjCUc4AZZnRh","text":{"elements":[{"text_run":{"content":"證券存入功能是指投資者透過證券交易平台將資金轉入證券帳戶的操作。投資者即可方便地將資金轉入證券帳戶，隨時隨地參與證券交易和投資活動。","text_element_style":{"bold":false,"inline_code":false,"italic":false,"strikethrough":false,"underline":false}}}],"style":{"align":1,"folded":false}}},{"block_id":"PkfEd1jrRotfpyxKZ1ccTdR4ncc","block_type":2,"parent_id":"L4s3d5sqqoP99gxwjCUc4AZZnRh","text":{"elements":[{"text_run":{"content":"Whale系統包含了存入申請、存入明細、便捷導入參數設置、電子郵件通知券商等功能，流程支援了不同角色的審核要求，有效地提升了證券存入的精確性。整體流程架構如下：","text_element_style":{"bold":false,"inline_code":false,"italic":false,"strikethrough":false,"underline":false}}}],"style":{"align":1,"folded":false}}},{"block_id":"SpW4drN0EobodfxSXtkcQ3x4nfe","block_type":43,"board":{"height":408,"token":"LmxHwUyIbhPgxvbvVoccR0LSnUd","width":745},"parent_id":"L4s3d5sqqoP99gxwjCUc4AZZnRh"},{"block_id":"VF04dDS4yokytDxZiYFcBBTenBf","block_type":2,"parent_id":"L4s3d5sqqoP99gxwjCUc4AZZnRh","text":{"elements":[{"text_run":{"content":"","text_element_style":{"bold":false,"inline_code":false,"italic":false,"strikethrough":false,"underline":false}}}],"style":{"align":1,"folded":false}}},{"block_id":"AUASd9CY6ohLEQxixhVcYVafnXc","block_type":3,"heading1":{"elements":[{"text_run":{"content":"二、操作說明","text_element_style":{"bold":false,"inline_code":false,"italic":false,"strikethrough":false,"underline":false}}}],"style":{"align":1,"folded":false}},"parent_id":"L4s3d5sqqoP99gxwjCUc4AZZnRh"},{"block_id":"DyDgd701toh4Bqx33jucAW71nSb","block_type":19,"callout":{"background_color":6,"border_color":6,"emoji_id":"round_pushpin"},"children":["QoGQdkceSo8kFBx5BGDc9cW7nic"],"parent_id":"L4s3d5sqqoP99gxwjCUc4AZZnRh"},{"block_id":"QoGQdkceSo8kFBx5BGDc9cW7nic","block_type":2,"parent_id":"DyDgd701toh4Bqx33jucAW71nSb","text":{"elements":[{"text_run":{"content":"菜單入口：證券管理-證券存入","text_element_style":{"bold":false,"inline_code":false,"italic":false,"strikethrough":false,"underline":false}}}],"style":{"align":1,"folded":false}}},{"block_id":"GJcndN1yOo1Zrjx6jlRcCUZbnBc","block_type":4,"heading2":{"elements":[{"text_run":{"content":"存入申請","text_element_style":{"bold":false,"inline_code":false,"italic":false,"strikethrough":false,"underline":false}}}],"style":{"align":1,"folded":false}},"parent_id":"L4s3d5sqqoP99gxwjCUc4AZZnRh"},{"block_id":"IcLudf8gMoS0oQxMU66coVfLnmc","block_type":2,"parent_id":"L4s3d5sqqoP99gxwjCUc4AZZnRh","text":{"elements":[{"text_run":{"content":"證券存入申請為用戶方提出，申請的內容包含了券商資訊、帳戶資訊、證券詳情與備註4大部分。WHALE使用者可以手動幫助客戶進行證券入倉并根據客戶提交的申請進行駁回、提交審批、通知券商等操作。","text_element_style":{"bold":false,"inline_code":false,"italic":false,"strikethrough":false,"underline":false}}}],"style":{"align":1,"folded":false}}},{"block_id":"X3LhdGYesojcklxux7xcOjZln8c","block_type":12,"bullet":{"elements":[{"text_run":{"content":"手工入倉","text_element_style":{"bold":false,"inline_code":false,"italic":false,"strikethrough":false,"underline":false}}}],"style":{"align":1,"folded":false}},"parent_id":"L4s3d5sqqoP99gxwjCUc4AZZnRh"},{"block_id":"Uni6dxUrHodJYMxNbafc19dlnNe","block_type":2,"parent_id":"L4s3d5sqqoP99gxwjCUc4AZZnRh","text":{"elements":[{"text_run":{"content":"適用於使用者聯絡後台操作員進行手動新增轉入申請記錄的場景，操作員需要依序填寫客戶的證券資訊、帳戶資訊以及證券的明細資訊。","text_element_style":{"bold":false,"inline_code":false,"italic":false,"strikethrough":false,"underline":false}}}],"style":{"align":1,"folded":false}}},{"block_id":"EaYhdtgRAoUL9Ex2PsBcbYfInRf","block_type":27,"image":{"align":2,"height":2469,"token":"Rs8lbixwro3MMExotmlcy7Uqnwe","width":2076},"parent_id":"L4s3d5sqqoP99gxwjCUc4AZZnRh"},{"block_id":"PJhzdM6NloQTtxx9MWtcy8m0nUg","block_type":12,"bullet":{"elements":[{"text_run":{"content":"駁回（","text_element_style":{"bold":false,"inline_code":false,"italic":false,"strikethrough":false,"underline":false}}},{"text_run":{"content":"可批量操作）","text_element_style":{"bold":true,"inline_code":false,"italic":false,"strikethrough":false,"underline":false}}},{"text_run":{"content":"：若客戶遞交證券存入申請資料有誤或使用者反饋本次申請無效時，操作員可以進行【駁回】操作","text_element_style":{"bold":false,"inline_code":false,"italic":false,"strikethrough":false,"underline":false}}}],"style":{"align":1,"folded":false}},"parent_id":"L4s3d5sqqoP99gxwjCUc4AZZnRh"},{"block_id":"SH9ydf0lqoDA4Ix7c7icwBFhnug","block_type":12,"bullet":{"elements":[{"text_run":{"content":"通知券商：由於轉倉業務需要對方券商的配合，在實際操作過程中，為了能夠順利轉入，用戶通常會聯絡券商及時處理。此功能將提供郵件發送功能，並根據郵件發送的結果顯示給用戶是否已經通知了券商，以便於用戶進一步處理業務。","text_element_style":{"bold":false,"inline_code":false,"italic":false,"strikethrough":false,"underline":false}}}],"style":{"align":1,"folded":false}},"children":["X3yZd84HPoeGxTxD9OFcuuUgnBg","LDeTdJ3yioO1cJx4oercnaIknhe","Rs4YdZtNLopiNEx8NeRcGr1rnSe","MlWZd2u7Ao4L7Ix7KXTcwMjRngg"],"parent_id":"L4s3d5sqqoP99gxwjCUc4AZZnRh"},{"block_id":"X3yZd84HPoeGxTxD9OFcuuUgnBg","block_type":12,"bullet":{"elements":[{"text_run":{"content":"選擇需要寄送郵件的券商機構，系統會自動帶出對方券商的郵件地址，操作員可檢查郵箱是否正確","text_element_style":{"bold":false,"inline_code":false,"italic":false,"strikethrough":false,"underline":false}}}],"style":{"align":1,"folded":false}},"parent_id":"SH9ydf0lqoDA4Ix7c7icwBFhnug"},{"block_id":"LDeTdJ3yioO1cJx4oercnaIknhe","block_type":12,"bullet":{"elements":[{"text_run":{"content":"選擇目標券商下的涉及到的證券轉入申請明細（已發送過的證券申請將被剔除）","text_element_style":{"bold":false,"inline_code":false,"italic":false,"strikethrough":false,"underline":false}}}],"style":{"align":1,"folded":false}},"parent_id":"SH9ydf0lqoDA4Ix7c7icwBFhnug"},{"block_id":"Rs4YdZtNLopiNEx8NeRcGr1rnSe","block_type":12,"bullet":{"elements":[{"text_run":{"content":"預覽郵件內容，確認無誤後點選發送","text_element_style":{"bold":false,"inline_code":false,"italic":false,"strikethrough":false,"underline":false}}}],"style":{"align":1,"folded":false}},"parent_id":"SH9ydf0lqoDA4Ix7c7icwBFhnug"},{"block_id":"MlWZd2u7Ao4L7Ix7KXTcwMjRngg","block_type":12,"bullet":{"elements":[{"text_run":{"content":"至郵件發送記錄頁面中查看發送狀態","text_element_style":{"bold":false,"inline_code":false,"italic":false,"strikethrough":false,"underline":false}}}],"style":{"align":1,"folded":false}},"parent_id":"SH9ydf0lqoDA4Ix7c7icwBFhnug"},{"block_id":"ATh7daaiIofwoQxrnnocmNlLn7g","block_type":24,"children":["UvlzdVOzsoA7tnxH8aEcoXjUnNd","V6LXd4U5UoVfbBxtaSmcvQE5nGc"],"grid":{"column_size":2},"parent_id":"L4s3d5sqqoP99gxwjCUc4AZZnRh"},{"block_id":"UvlzdVOzsoA7tnxH8aEcoXjUnNd","block_type":25,"children":["FEBqdEJ5NobR9ExmX58cN2Sdn9e"],"grid_column":{"width_ratio":49},"parent_id":"ATh7daaiIofwoQxrnnocmNlLn7g"},{"block_id":"FEBqdEJ5NobR9ExmX58cN2Sdn9e","block_type":27,"image":{"align":2,"height":1330,"token":"Pe7GbOsfAo6RQqxgTa8c3vbWnde","width":2858},"parent_id":"UvlzdVOzsoA7tnxH8aEcoXjUnNd"},{"block_id":"V6LXd4U5UoVfbBxtaSmcvQE5nGc","block_type":25,"children":["E3xpdDIRfoEfqwxjrmIc1UC5nMh"],"grid_column":{"width_ratio":49},"parent_id":"ATh7daaiIofwoQxrnnocmNlLn7g"},{"block_id":"E3xpdDIRfoEfqwxjrmIc1UC5nMh","block_type":27,"image":{"align":2,"height":1332,"token":"G1o5bwjNKorKgTxljAHcBMB0nDc","width":2856},"parent_id":"V6LXd4U5UoVfbBxtaSmcvQE5nGc"},{"block_id":"PTzadtBEvojqXrxMfXCchaT1nrh","block_type":24,"children":["MBpRdFTFiokOIDx67JYcptKAnxb","UP71dV5yUo6NYKx9vcwclRvxncg"],"grid":{"column_size":2},"parent_id":"L4s3d5sqqoP99gxwjCUc4AZZnRh"},{"block_id":"MBpRdFTFiokOIDx67JYcptKAnxb","block_type":25,"children":["PyrxdbFRgodINCxpJlDclgO2nad"],"grid_column":{"width_ratio":50},"parent_id":"PTzadtBEvojqXrxMfXCchaT1nrh"},{"block_id":"PyrxdbFRgodINCxpJlDclgO2nad","block_type":27,"image":{"align":2,"height":599,"token":"PTVDbTCJVoZBlUxF6MZcGEZXn8b","width":1280},"parent_id":"MBpRdFTFiokOIDx67JYcptKAnxb"},{"block_id":"UP71dV5yUo6NYKx9vcwclRvxncg","block_type":25,"children":["K1Gpd5DnPookvVxEF5Mcf2odntg"],"grid_column":{"width_ratio":50},"parent_id":"PTzadtBEvojqXrxMfXCchaT1nrh"},{"block_id":"K1Gpd5DnPookvVxEF5Mcf2odntg","block_type":27,"image":{"align":2,"height":624,"token":"BlwubaEs5oJyRsxfs4kcyvOFnWf","width":1280},"parent_id":"UP71dV5yUo6NYKx9vcwclRvxncg"},{"block_id":"QwfvdRv7toHaFMxG5dhc86jYnPe","block_type":12,"bullet":{"elements":[{"text_run":{"content":"提交（","text_element_style":{"bold":false,"inline_code":false,"italic":false,"strikethrough":false,"underline":false}}},{"text_run":{"content":"可批量操作）","text_element_style":{"bold":true,"inline_code":false,"italic":false,"strikethrough":false,"underline":false}}},{"text_run":{"content":"：經過操作人員初步審查無誤後，可以將申請提交至下一節點的操作人員進行審核-入倉操作","text_element_style":{"bold":false,"inline_code":false,"italic":false,"strikethrough":false,"underline":false}}}],"style":{"align":1,"folded":false}},"parent_id":"L4s3d5sqqoP99gxwjCUc4AZZnRh"},{"block_id":"CHj5dv9yco18aSxzpSJcMaOknyS","block_type":12,"bullet":{"elements":[{"text_run":{"content":"編輯：若操作員在處理轉入申請時，從客戶方得知券商已通知或未通知的信息，可以透過【編輯】按鈕進行修改通知狀態，以保證對方券商是否知曉需要處理證券轉倉的信息與實際情況相符","text_element_style":{"bold":false,"inline_code":false,"italic":false,"strikethrough":false,"underline":false}}}],"style":{"align":1,"folded":false}},"parent_id":"L4s3d5sqqoP99gxwjCUc4AZZnRh"},{"block_id":"ReKmdnCtuoKcG6xHzb4cKcvvnvc","block_type":27,"image":{"align":2,"height":1380,"token":"QV1ebO67IoH0nwxN9OKcyFmHn9f","width":3830},"parent_id":"L4s3d5sqqoP99gxwjCUc4AZZnRh"},{"block_id":"Tt8UdPUvTop900xlVKkcwh90nMe","block_type":12,"bullet":{"elements":[{"text_run":{"content":"指標卡","text_element_style":{"bold":false,"inline_code":false,"italic":false,"strikethrough":false,"underline":false}}}],"style":{"align":1,"folded":false}},"parent_id":"L4s3d5sqqoP99gxwjCUc4AZZnRh"},{"block_id":"SYCYdOQodo3FMrx3UoKcUg7xnAf","block_type":2,"parent_id":"L4s3d5sqqoP99gxwjCUc4AZZnRh","text":{"elements":[{"text_run":{"content":"若券商的證券轉入業務量較大，可以透過系統的分類展示卡進行精細化作業，指標卡的左右排布反映了業務操作的先後順序","text_element_style":{"bold":false,"inline_code":false,"italic":false,"strikethrough":false,"underline":false}}}],"style":{"align":1,"folded":false}}},{"block_id":"EaMHdfU3hoLmw3xksIzcYoHjnKg","block_type":27,"image":{"align":2,"height":1780,"token":"HggKbN1i8o3i4TxYy3Wcmgnjn1g","width":3818},"parent_id":"L4s3d5sqqoP99gxwjCUc4AZZnRh"},{"block_id":"Q8OsdwyMvoWszex05DucgVvZnqh","block_type":4,"heading2":{"elements":[{"text_run":{"content":"存入明細","text_element_style":{"bold":false,"inline_code":false,"italic":false,"strikethrough":false,"underline":false}}}],"style":{"align":1,"folded":false}},"parent_id":"L4s3d5sqqoP99gxwjCUc4AZZnRh"},{"block_id":"VFImduDLtoP7ipxg1ifcriMKnXb","block_type":2,"parent_id":"L4s3d5sqqoP99gxwjCUc4AZZnRh","text":{"elements":[{"text_run":{"content":"由於一個存入申請下可能存在多筆證券明細記錄，具體操作入倉的審核人員需要針對每筆存入明細進行仔細核對，審核通過後方可入倉。","text_element_style":{"bold":false,"inline_code":false,"italic":false,"strikethrough":false,"underline":false}}}],"style":{"align":1,"folded":false}}},{"block_id":"HSNZdadaAoMXlbx11hOczY8gnkb","block_type":12,"bullet":{"elements":[{"text_run":{"content":"修改：若在處理證券明細時，發現用戶提交的某筆具體的明細記錄有問題，可在與客戶確認無誤後可以透過【編輯】按鈕進行修正","text_element_style":{"bold":false,"inline_code":false,"italic":false,"strikethrough":false,"underline":false}}}],"style":{"align":1,"folded":false}},"children":["Wnqwd7zngoGdwuxX2I6cjiTcnIe"],"parent_id":"L4s3d5sqqoP99gxwjCUc4AZZnRh"},{"block_id":"Wnqwd7zngoGdwuxX2I6cjiTcnIe","block_type":12,"bullet":{"elements":[{"text_run":{"content":"修改的范围：股票名稱、託管商編號、子倉編號、證券明細數量、轉入成本、結單備註","text_element_style":{"bold":false,"inline_code":false,"italic":false,"strikethrough":false,"underline":false}}}],"style":{"align":1,"folded":false}},"parent_id":"HSNZdadaAoMXlbx11hOczY8gnkb"},{"block_id":"HxU1doRqAoG0qAx4BLNcu4bGnzc","block_type":27,"image":{"align":1,"height":1836,"token":"VCsIbKiGOoCzpNxrRC4cHIFzn5f","width":3818},"parent_id":"L4s3d5sqqoP99gxwjCUc4AZZnRh"},{"block_id":"SleJdvwagoJei5xNCeacRvnJnHh","block_type":12,"bullet":{"elements":[{"text_run":{"content":"删除：若在證券明細時，用戶反映提交的某筆具體的明細記錄不再進行轉入，可以透過【删除】按鈕直接刪除目標明細記錄","text_element_style":{"bold":false,"inline_code":false,"italic":false,"strikethrough":false,"underline":false}}}],"style":{"align":1,"folded":false}},"parent_id":"L4s3d5sqqoP99gxwjCUc4AZZnRh"},{"block_id":"BHoHdi7UKoHLLlxx70zcjynGnEf","block_type":12,"bullet":{"elements":[{"text_run":{"content":"生成SI指令（","text_element_style":{"bold":false,"inline_code":false,"italic":false,"strikethrough":false,"underline":false}}},{"text_run":{"content":"可批量操作）","text_element_style":{"bold":true,"inline_code":false,"italic":false,"strikethrough":false,"underline":false}}},{"text_run":{"content":"：由於轉倉業務需要在CCASS裡填寫必要的SI信息，生成SI指令功能可以將這些必要的信息以文件的形式自動保存，供用戶進行上傳CCASS，以免於手動在CCASS系統錄入。產生的SI指令也可以在「SI指令清單」選單下進行詳情查看、匯出等操作","text_element_style":{"bold":false,"inline_code":false,"italic":false,"strikethrough":false,"underline":false}}}],"style":{"align":1,"folded":false}},"parent_id":"L4s3d5sqqoP99gxwjCUc4AZZnRh"},{"block_id":"SMLAdOk6LoOAyoxwg4YclgM3nue","block_type":24,"children":["L6vbdlLORomTwAxvH6vcxJsPnLh","DRqDdfUENoPuM0xBXo6cRhcin9b"],"grid":{"column_size":2},"parent_id":"L4s3d5sqqoP99gxwjCUc4AZZnRh"},{"block_id":"L6vbdlLORomTwAxvH6vcxJsPnLh","block_type":25,"children":["BWSBd5AtnoBKGUx3QRocwHIXnjc"],"grid_column":{"width_ratio":50},"parent_id":"SMLAdOk6LoOAyoxwg4YclgM3nue"},{"block_id":"BWSBd5AtnoBKGUx3QRocwHIXnjc","block_type":27,"image":{"align":2,"height":1824,"token":"Sd08b1d1yoPMeaxsM2oc98HOnna","width":3828},"parent_id":"L6vbdlLORomTwAxvH6vcxJsPnLh"},{"block_id":"DRqDdfUENoPuM0xBXo6cRhcin9b","block_type":25,"children":["HCADd0mKWoCCclxzfvGchD1uncq"],"grid_column":{"width_ratio":50},"parent_id":"SMLAdOk6LoOAyoxwg4YclgM3nue"},{"block_id":"HCADd0mKWoCCclxzfvGchD1uncq","block_type":27,"image":{"align":2,"height":1796,"token":"IwfnbUH2oorMwFxIcS5cCZlGnqd","width":3822},"parent_id":"DRqDdfUENoPuM0xBXo6cRhcin9b"},{"block_id":"RFfIdaFAPoe0f0xmkwMcPnBtn5f","block_type":12,"bullet":{"elements":[{"text_run":{"content":"編輯SI指令（","text_element_style":{"bold":false,"inline_code":false,"italic":false,"strikethrough":false,"underline":false}}},{"text_run":{"content":"可批量操作）","text_element_style":{"bold":true,"inline_code":false,"italic":false,"strikethrough":false,"underline":false}}},{"text_run":{"content":"：若需要對已經產生的SI資訊進行修改，可以點選【編輯SI資訊】對目標欄位進行修正","text_element_style":{"bold":false,"inline_code":false,"italic":false,"strikethrough":false,"underline":false}}}],"style":{"align":1,"folded":false}},"parent_id":"L4s3d5sqqoP99gxwjCUc4AZZnRh"},{"block_id":"EtvvdPxxNoveQhx7okac6QAjnbz","block_type":27,"image":{"align":2,"height":1322,"token":"CXNObXfNhoyoLoxtqwDcqZ5nnxb","width":2872},"parent_id":"L4s3d5sqqoP99gxwjCUc4AZZnRh"},{"block_id":"X1s2dhVwuoCulrxWaQFcfkVfnvg","block_type":12,"bullet":{"elements":[{"text_run":{"content":"處理-成功提交/失敗提交（","text_element_style":{"bold":false,"inline_code":false,"italic":false,"strikethrough":false,"underline":false}}},{"text_run":{"content":"可批量操作）","text_element_style":{"bold":true,"inline_code":false,"italic":false,"strikethrough":false,"underline":false}}},{"text_run":{"content":"：若操作人員認定某個明細沒有問題，可以點選【處理】選擇【成功提交】，反之選擇【失敗提交】。","text_element_style":{"bold":false,"inline_code":false,"italic":false,"strikethrough":false,"underline":false}}}],"style":{"align":1,"folded":false}},"children":["C2bZdzlFJow5LPxFVsacTpflnxf","XInLdngdJoIpH1xcjcTcr8Q3nHg","XzxTdpteJoVdBux0PJJcbHNFnje","JBHAdYzxUo94mhxtwlCcF1ftnHe"],"parent_id":"L4s3d5sqqoP99gxwjCUc4AZZnRh"},{"block_id":"C2bZdzlFJow5LPxFVsacTpflnxf","block_type":12,"bullet":{"elements":[{"text_run":{"content":"處理完畢後，流程進行至下一節點，需要在工單中心進行審核，審核通過購，股票成功入倉","text_element_style":{"bold":false,"inline_code":false,"italic":false,"strikethrough":false,"underline":false}}}],"style":{"align":1,"folded":false}},"parent_id":"X1s2dhVwuoCulrxWaQFcfkVfnvg"},{"block_id":"XInLdngdJoIpH1xcjcTcr8Q3nHg","block_type":27,"image":{"align":2,"height":1782,"token":"HjJ4bfRmYobd1Hxg6rVcsZ0Tnic","width":3824},"parent_id":"X1s2dhVwuoCulrxWaQFcfkVfnvg"},{"block_id":"XzxTdpteJoVdBux0PJJcbHNFnje","block_type":12,"bullet":{"elements":[{"text_run":{"content":"若用戶轉入的證券為實體股票，可在處理時同時手動設定實體股票的解凍時間，實體股票將在設定的時間點自動解凍，如若未設定時間，流程通過後則立即解凍","text_element_style":{"bold":false,"inline_code":false,"italic":false,"strikethrough":false,"underline":false}}}],"style":{"align":1,"folded":false}},"parent_id":"X1s2dhVwuoCulrxWaQFcfkVfnvg"},{"block_id":"JBHAdYzxUo94mhxtwlCcF1ftnHe","block_type":27,"image":{"align":2,"height":1566,"token":"TUtGbejRkouYMDxKszzcKVzxn6g","width":3828},"parent_id":"X1s2dhVwuoCulrxWaQFcfkVfnvg"},{"block_id":"GcSMd30Uko1EW2xTOaDcgvgpnUb","block_type":12,"bullet":{"elements":[{"text_run":{"content":"審批（","text_element_style":{"bold":false,"inline_code":false,"italic":false,"strikethrough":false,"underline":false}}},{"text_run":{"content":"可批量操作）","text_element_style":{"bold":true,"inline_code":false,"italic":false,"strikethrough":false,"underline":false}}},{"text_run":{"content":"：處理結果提交後，操作列出現【審核】按鈕，點選可以召喚出工單審核頁面","text_element_style":{"bold":false,"inline_code":false,"italic":false,"strikethrough":false,"underline":false}}}],"style":{"align":1,"folded":false}},"children":["C3LEdK4jSojQ8lx3iTkcmml5nYb"],"parent_id":"L4s3d5sqqoP99gxwjCUc4AZZnRh"},{"block_id":"C3LEdK4jSojQ8lx3iTkcmml5nYb","block_type":12,"bullet":{"elements":[{"text_run":{"content":"處理完畢後，流程進行至下一節點，需要在工單中心進行審核，審核通過購，股票成功入倉","text_element_style":{"bold":false,"inline_code":false,"italic":false,"strikethrough":false,"underline":false}}}],"style":{"align":1,"folded":false}},"parent_id":"GcSMd30Uko1EW2xTOaDcgvgpnUb"},{"block_id":"ONWRdpfmMoYGWrxplxac4gIzngf","block_type":27,"image":{"align":2,"height":1943,"token":"KvRBb19f0oCmahxZVzvcI2PQnsd","width":3906},"parent_id":"L4s3d5sqqoP99gxwjCUc4AZZnRh"},{"block_id":"X03DdPITXosfiAxCzaAckZGDn9f","block_type":12,"bullet":{"elements":[{"text_run":{"content":"提交解凍（","text_element_style":{"bold":false,"inline_code":false,"italic":false,"strikethrough":false,"underline":false}}},{"text_run":{"content":"可批量操作）","text_element_style":{"bold":true,"inline_code":false,"italic":false,"strikethrough":false,"underline":false}}},{"text_run":{"content":"：若客戶轉入的證券為實體股票，且在處理時，設定了解凍時間，但在期限到達前想要提前對實體股票進行處理，可以進行手動解凍，提交后需再次進行審批，審批通過後立即解凍成功。","text_element_style":{"bold":false,"inline_code":false,"italic":false,"strikethrough":false,"underline":false}}}],"style":{"align":1,"folded":false}},"parent_id":"L4s3d5sqqoP99gxwjCUc4AZZnRh"},{"block_id":"YppIdGevso8j3dxTdITcfLHKn9d","block_type":27,"image":{"align":2,"height":1162,"token":"I2XsbjBPeo1htexdyWfcZm7VnXf","width":3822},"parent_id":"L4s3d5sqqoP99gxwjCUc4AZZnRh"},{"block_id":"E8Grdjj8KoAFTyxCjTicBHcSnYe","block_type":27,"image":{"align":2,"height":1866,"token":"TGOob6vbroPLL8xiXOgcZoZKn8e","width":3824},"parent_id":"L4s3d5sqqoP99gxwjCUc4AZZnRh"},{"block_id":"UyZVdtnRCoJnwBxOz7RcEyQXnwK","block_type":4,"heading2":{"elements":[{"text_run":{"content":"存入限制","text_element_style":{"bold":false,"inline_code":false,"italic":false,"strikethrough":false,"underline":false}}}],"style":{"align":1,"folded":false}},"parent_id":"L4s3d5sqqoP99gxwjCUc4AZZnRh"},{"block_id":"L9ANd5YPxokN60xbv4IcP6jgn8f","block_type":2,"parent_id":"L4s3d5sqqoP99gxwjCUc4AZZnRh","text":{"elements":[{"text_run":{"content":"為了提高證券准入的成功率，杜絕一些諸如已退市股票的轉入，可以透過設定股票黑名單的方式提前控制目標股票的轉入限制。系統提供了單筆限制與批量限制功能：","text_element_style":{"bold":false,"inline_code":false,"italic":false,"strikethrough":false,"underline":false}}}],"style":{"align":1,"folded":false}}},{"block_id":"R0q5diP7JonlUtxrYUHcBMK1n9R","block_type":12,"bullet":{"elements":[{"text_run":{"content":"單筆限制","text_element_style":{"bold":false,"inline_code":false,"italic":false,"strikethrough":false,"underline":false}}}],"style":{"align":1,"folded":false}},"parent_id":"L4s3d5sqqoP99gxwjCUc4AZZnRh"},{"block_id":"I3gfdVoEBoUEmmxjXWWc6JHznZf","block_type":27,"image":{"align":2,"height":1856,"token":"M7Q5bgrIUoyYFkxZK0Qc6CUqn7c","width":3814},"parent_id":"L4s3d5sqqoP99gxwjCUc4AZZnRh"},{"block_id":"Nn1Cd4pa4oYkFRxjbYRcKqUZnAc","block_type":12,"bullet":{"elements":[{"text_run":{"content":"批量限制","text_element_style":{"bold":false,"inline_code":false,"italic":false,"strikethrough":false,"underline":false}}}],"style":{"align":1,"folded":false}},"parent_id":"L4s3d5sqqoP99gxwjCUc4AZZnRh"},{"block_id":"AYZQdEasxo2BSWxFeuKc46annmb","block_type":24,"children":["INEEdQbifocBRoxKSAkcsZ5KnAb","RTvAdiA8BoXbDdxdnRLcpCYPn2b"],"grid":{"column_size":2},"parent_id":"L4s3d5sqqoP99gxwjCUc4AZZnRh"},{"block_id":"INEEdQbifocBRoxKSAkcsZ5KnAb","block_type":25,"children":["KyHLdqOE0oCKTtxFCa1cIMsunmd","Kh0UdPgzSo7RrcxgmlJcLc0en9R","UvRudB0QQoLb2mxykdnck48Unqc"],"grid_column":{"width_ratio":50},"parent_id":"AYZQdEasxo2BSWxFeuKc46annmb"},{"block_id":"KyHLdqOE0oCKTtxFCa1cIMsunmd","block_type":2,"parent_id":"INEEdQbifocBRoxKSAkcsZ5KnAb","text":{"elements":[{"text_run":{"content":"入口","text_element_style":{"bold":false,"inline_code":false,"italic":false,"strikethrough":false,"underline":false}}}],"style":{"align":1,"folded":false}}},{"block_id":"Kh0UdPgzSo7RrcxgmlJcLc0en9R","block_type":27,"image":{"align":2,"height":1844,"token":"ZdqpbCPZJoHcN5xprGKcq2Sonie","width":3824},"parent_id":"INEEdQbifocBRoxKSAkcsZ5KnAb"},{"block_id":"UvRudB0QQoLb2mxykdnck48Unqc","block_type":2,"parent_id":"INEEdQbifocBRoxKSAkcsZ5KnAb","text":{"elements":[{"text_run":{"content":"","text_element_style":{"bold":false,"inline_code":false,"italic":false,"strikethrough":false,"underline":false}}}],"style":{"align":1,"folded":false}}},{"block_id":"RTvAdiA8BoXbDdxdnRLcpCYPn2b","block_type":25,"children":["SVc8dvmNeoFqIlxc0AKcOK9snhh","Ly9GdPErnowZYaxU06FcR4iun0c","EYvCdQuBPoV8QvxGDdHcgdIvnvd"],"grid_column":{"width_ratio":50},"parent_id":"AYZQdEasxo2BSWxFeuKc46annmb"},{"block_id":"SVc8dvmNeoFqIlxc0AKcOK9snhh","block_type":2,"parent_id":"RTvAdiA8BoXbDdxdnRLcpCYPn2b","text":{"elements":[{"text_run":{"content":"範本","text_element_style":{"bold":false,"inline_code":false,"italic":false,"strikethrough":false,"underline":false}}}],"style":{"align":1,"folded":false}}},{"block_id":"Ly9GdPErnowZYaxU06FcR4iun0c","block_type":27,"image":{"align":2,"height":372,"token":"ZmWNbUItNopz8Cx15DJcl5cUneh","width":652},"parent_id":"RTvAdiA8BoXbDdxdnRLcpCYPn2b"},{"block_id":"EYvCdQuBPoV8QvxGDdHcgdIvnvd","block_type":2,"parent_id":"RTvAdiA8BoXbDdxdnRLcpCYPn2b","text":{"elements":[{"text_run":{"content":"","text_element_style":{"bold":false,"inline_code":false,"italic":false,"strikethrough":false,"underline":false}}}],"style":{"align":1,"folded":false}}},{"block_id":"NuKFdbC4oo8wKAxTVcGckUymnug","block_type":4,"heading2":{"elements":[{"text_run":{"content":"郵件發送記錄","text_element_style":{"bold":false,"inline_code":false,"italic":false,"strikethrough":false,"underline":false}}}],"style":{"align":1,"folded":false}},"parent_id":"L4s3d5sqqoP99gxwjCUc4AZZnRh"},{"block_id":"Nd52dwmjhomX8fxXP63cBdk0nuf","block_type":2,"parent_id":"L4s3d5sqqoP99gxwjCUc4AZZnRh","text":{"elements":[{"text_run":{"content":"用戶將目標存入申請通知券商後，相應的郵件記錄將會被保存，以用於後續進行問題追蹤。","text_element_style":{"bold":false,"inline_code":false,"italic":false,"strikethrough":false,"underline":false}}}],"style":{"align":1,"folded":false}}},{"block_id":"SOt3dCY5HoebwnxahpZcxtk7n2b","block_type":27,"image":{"align":2,"height":1856,"token":"QC2gboHuWofvXSxXF40cXYMEnsh","width":3834},"parent_id":"L4s3d5sqqoP99gxwjCUc4AZZnRh"},{"block_id":"HnahdF66zorG3Xx872FcDhfDn7V","block_type":3,"heading1":{"elements":[{"text_run":{"content":"","text_element_style":{"bold":false,"inline_code":false,"italic":false,"strikethrough":false,"underline":false}}}],"style":{"align":1,"folded":false}},"parent_id":"L4s3d5sqqoP99gxwjCUc4AZZnRh"},{"block_id":"TERFdqSHuot6otxYmRGcMnBDnkg","block_type":2,"parent_id":"L4s3d5sqqoP99gxwjCUc4AZZnRh","text":{"elements":[{"text_run":{"content":"","text_element_style":{"bold":false,"inline_code":false,"italic":false,"strikethrough":false,"underline":false}}}],"style":{"align":1,"folded":false}}}]}