{"obj_edit_time":"1697443580","blocks":[{"block_id":"MKDNd8tRgojcjIxMExBcPOmgnXg","block_type":1,"children":["LWFod8CJdoLKsyxfC5PclG3CnUe"],"page":{"elements":[{"text_run":{"content":"Customer Manage","text_element_style":{"bold":false,"inline_code":false,"italic":false,"strikethrough":false,"underline":false}}}],"style":{"align":1}},"parent_id":""},{"block_id":"LWFod8CJdoLKsyxfC5PclG3CnUe","block_type":2,"parent_id":"MKDNd8tRgojcjIxMExBcPOmgnXg","text":{"elements":[{"text_run":{"content":"","text_element_style":{"bold":false,"inline_code":false,"italic":false,"strikethrough":false,"underline":false}}}],"style":{"align":1,"folded":false}}}]}