{"obj_edit_time":"1725244623","blocks":[{"block_id":"QBTEdMOqnotmLcxrwGRcMfxknYg","block_type":1,"children":["X2rdd3cZHoG5Jxxkpa3cQiPMncf","Q3gWdZg7aosVh3xfAYVcVkkCnte","ZCCQdiMghoiu1qxbweUc3ZeUnXe","RGeHdT930oWjkXxHGmHcy1KOn0g","FZrvds2BPo7B3exeQ9Xc5qdPnGa","SRbRd4j57onU7ax3IyEcflodnJf","FXE2dVG9Uo8ytnxBOTNcsgqhnff","JjcaddjNSo4uN6xueZdcZ4CNn1c","STAZdtKgNogquXxKmCEcQKNin2I","LbPUdSUNFosrDIxNNmWcQS6unve","LI8fdKffxoR4rlxb9lQcgE4nnUb","D9sudbabdoEEAlxBmaXc3Ga5nRf"],"page":{"elements":[{"text_run":{"content":"7.1 融資利息","text_element_style":{"bold":false,"inline_code":false,"italic":false,"strikethrough":false,"underline":false}}}],"style":{"align":1}},"parent_id":""},{"block_id":"X2rdd3cZHoG5Jxxkpa3cQiPMncf","block_type":4,"heading2":{"elements":[{"text_run":{"content":"7.1A 問：融資利息如何查看或額免？","text_element_style":{"bold":false,"inline_code":false,"italic":false,"strikethrough":false,"underline":false}}}],"style":{"align":1,"folded":false}},"parent_id":"QBTEdMOqnotmLcxrwGRcMfxknYg"},{"block_id":"Q3gWdZg7aosVh3xfAYVcVkkCnte","block_type":2,"parent_id":"QBTEdMOqnotmLcxrwGRcMfxknYg","text":{"elements":[{"text_run":{"content":"答：","text_element_style":{"bold":true,"inline_code":false,"italic":false,"strikethrough":false,"underline":false}}},{"text_run":{"content":"在「清算管理＞融券管理＞融資利息賬單」頁面以賬戶號碼查詢客戶的融資利息","text_element_style":{"bold":false,"inline_code":false,"italic":false,"strikethrough":false,"underline":false}}}],"style":{"align":1,"folded":false}}},{"block_id":"ZCCQdiMghoiu1qxbweUc3ZeUnXe","block_type":27,"image":{"align":2,"height":1384,"token":"EcCEbfej8o7UdsxCyTlcodl5n2c","width":2498},"parent_id":"QBTEdMOqnotmLcxrwGRcMfxknYg"},{"block_id":"RGeHdT930oWjkXxHGmHcy1KOn0g","block_type":27,"image":{"align":2,"height":1360,"token":"ONLFbyzGQokfcyxEhM7c4Wjpnyg","width":2154},"parent_id":"QBTEdMOqnotmLcxrwGRcMfxknYg"},{"block_id":"FZrvds2BPo7B3exeQ9Xc5qdPnGa","block_type":2,"parent_id":"QBTEdMOqnotmLcxrwGRcMfxknYg","text":{"elements":[{"text_run":{"content":"","text_element_style":{"bold":false,"inline_code":false,"italic":false,"strikethrough":false,"underline":false}}}],"style":{"align":1,"folded":false}}},{"block_id":"SRbRd4j57onU7ax3IyEcflodnJf","block_type":4,"heading2":{"elements":[{"text_run":{"content":"7.1B 問：如何能調整到當天的利息？","text_element_style":{"bold":false,"inline_code":false,"italic":false,"strikethrough":false,"underline":false}}}],"style":{"align":1,"folded":false}},"parent_id":"QBTEdMOqnotmLcxrwGRcMfxknYg"},{"block_id":"FXE2dVG9Uo8ytnxBOTNcsgqhnff","block_type":2,"parent_id":"QBTEdMOqnotmLcxrwGRcMfxknYg","text":{"elements":[{"text_run":{"content":"答：沒有調整到當天融資利息的功能，需要下一天執行到日終到 \"資金清算\" 後，才能調整到今天的利息。","text_element_style":{"bold":false,"inline_code":false,"italic":false,"strikethrough":false,"underline":false}}}],"style":{"align":1,"folded":false}}},{"block_id":"JjcaddjNSo4uN6xueZdcZ4CNn1c","block_type":2,"parent_id":"QBTEdMOqnotmLcxrwGRcMfxknYg","text":{"elements":[{"text_run":{"content":"","text_element_style":{"bold":false,"inline_code":false,"italic":false,"strikethrough":false,"underline":false}}}],"style":{"align":1,"folded":false}}},{"block_id":"STAZdtKgNogquXxKmCEcQKNin2I","block_type":4,"heading2":{"elements":[{"text_run":{"content":"7.1C 問：如何提早發放利息給客戶？","text_element_style":{"bold":false,"inline_code":false,"italic":false,"strikethrough":false,"underline":false}}}],"style":{"align":1,"folded":false}},"parent_id":"QBTEdMOqnotmLcxrwGRcMfxknYg"},{"block_id":"LbPUdSUNFosrDIxNNmWcQS6unve","block_type":2,"parent_id":"QBTEdMOqnotmLcxrwGRcMfxknYg","text":{"elements":[{"text_run":{"content":"答：","text_element_style":{"bold":true,"inline_code":false,"italic":false,"strikethrough":false,"underline":false}}},{"text_run":{"content":"「清算管理＞融資管理」選「存款利息 / 融資利息」，點擊「提前結算」可以提早發放利息 / 收取融資利息結欠。","text_element_style":{"bold":false,"inline_code":false,"italic":false,"strikethrough":false,"underline":false}}}],"style":{"align":1,"folded":false}}},{"block_id":"LI8fdKffxoR4rlxb9lQcgE4nnUb","block_type":27,"image":{"align":2,"height":1412,"token":"Iu0Ebc3DhoXpfRxzveMc5wponvg","width":2682},"parent_id":"QBTEdMOqnotmLcxrwGRcMfxknYg"},{"block_id":"D9sudbabdoEEAlxBmaXc3Ga5nRf","block_type":2,"parent_id":"QBTEdMOqnotmLcxrwGRcMfxknYg","text":{"elements":[{"text_run":{"content":"","text_element_style":{"bold":false,"inline_code":false,"italic":false,"strikethrough":false,"underline":false}}}],"style":{"align":1,"folded":false}}}]}