{"obj_edit_time":"1708917864","blocks":[{"block_id":"VWJRdn429ou7pGxspgicF05anvc","block_type":1,"children":["KUHAdkly8o9miYxg0UEcrg1bnRm","VflVdfrnlo5bw7xB1hecAjwJnMe","D8s9d3yEtogZudx5B5zcbpFqnqf","EzcpdbKjDoWT1Tx4kL1cvog4nxb","SOEDd0xqUoHjrPxmcYnctdemnyd","HfpMdNZgBoEAzixVHF5cTwV0nsc","FhzNdYggNo3c9BxBKKfcxza6n2d"],"page":{"elements":[{"text_run":{"content":"業務介紹","text_element_style":{"bold":false,"inline_code":false,"italic":false,"strikethrough":false,"underline":false}}}],"style":{"align":1}},"parent_id":""},{"block_id":"KUHAdkly8o9miYxg0UEcrg1bnRm","block_type":3,"heading1":{"elements":[{"text_run":{"content":"概述","text_element_style":{"bold":false,"inline_code":false,"italic":false,"strikethrough":false,"underline":false}}}],"style":{"align":1,"folded":false}},"parent_id":"VWJRdn429ou7pGxspgicF05anvc"},{"block_id":"VflVdfrnlo5bw7xB1hecAjwJnMe","block_type":2,"parent_id":"VWJRdn429ou7pGxspgicF05anvc","text":{"elements":[{"text_run":{"content":"經紀人管理模塊提供了對經紀人與客戶關系的管理，以及經紀人和團隊的管理功能。以下是對這些模塊的概述：","text_element_style":{"bold":false,"inline_code":false,"italic":false,"strikethrough":false,"underline":false}}}],"style":{"align":1,"folded":false}}},{"block_id":"D8s9d3yEtogZudx5B5zcbpFqnqf","block_type":13,"children":["LVC9dvz6coxbQVx4EfgccUHGnjl","Vp8kdkdHuopOG3xMDKFcst4hnnh","M7YodD3M0o1PaExzGmEcCYCZndd"],"ordered":{"elements":[{"text_run":{"content":"經紀人與客戶關系管理：","text_element_style":{"bold":false,"inline_code":false,"italic":false,"strikethrough":false,"underline":false}}}],"style":{"align":1,"folded":false}},"parent_id":"VWJRdn429ou7pGxspgicF05anvc"},{"block_id":"LVC9dvz6coxbQVx4EfgccUHGnjl","block_type":12,"bullet":{"elements":[{"text_run":{"content":"該模塊用于建立、管理和維護經紀人與客戶之間的關系。","text_element_style":{"bold":false,"inline_code":false,"italic":false,"strikethrough":false,"underline":false}}}],"style":{"align":1,"folded":false}},"parent_id":"D8s9d3yEtogZudx5B5zcbpFqnqf"},{"block_id":"Vp8kdkdHuopOG3xMDKFcst4hnnh","block_type":12,"bullet":{"elements":[{"text_run":{"content":"可以創建經紀人賬戶，並將其與相應的客戶關聯起來。","text_element_style":{"bold":false,"inline_code":false,"italic":false,"strikethrough":false,"underline":false}}}],"style":{"align":1,"folded":false}},"parent_id":"D8s9d3yEtogZudx5B5zcbpFqnqf"},{"block_id":"M7YodD3M0o1PaExzGmEcCYCZndd","block_type":12,"bullet":{"elements":[{"text_run":{"content":"可以查看和管理經紀人與客戶之間的關系，包括關聯的客戶列表、客戶的投資情況和交易記錄等。","text_element_style":{"bold":false,"inline_code":false,"italic":false,"strikethrough":false,"underline":false}}}],"style":{"align":1,"folded":false}},"parent_id":"D8s9d3yEtogZudx5B5zcbpFqnqf"},{"block_id":"EzcpdbKjDoWT1Tx4kL1cvog4nxb","block_type":13,"children":["KH5odbe0RoVRm4xYheycCYhqnDf","K9WJddC8Pov1X3xMTdLcj8agncg","KVFxdUkzForrJ8xmRX4cRPMunad"],"ordered":{"elements":[{"text_run":{"content":"經紀人和團隊管理：","text_element_style":{"bold":false,"inline_code":false,"italic":false,"strikethrough":false,"underline":false}}}],"style":{"align":1,"folded":false}},"parent_id":"VWJRdn429ou7pGxspgicF05anvc"},{"block_id":"KH5odbe0RoVRm4xYheycCYhqnDf","block_type":12,"bullet":{"elements":[{"text_run":{"content":"該模塊用于管理經紀人和團隊的信息和組織結構。","text_element_style":{"bold":false,"inline_code":false,"italic":false,"strikethrough":false,"underline":false}}}],"style":{"align":1,"folded":false}},"parent_id":"EzcpdbKjDoWT1Tx4kL1cvog4nxb"},{"block_id":"K9WJddC8Pov1X3xMTdLcj8agncg","block_type":12,"bullet":{"elements":[{"text_run":{"content":"可以創建和管理經紀人賬戶和團隊賬戶。","text_element_style":{"bold":false,"inline_code":false,"italic":false,"strikethrough":false,"underline":false}}}],"style":{"align":1,"folded":false}},"parent_id":"EzcpdbKjDoWT1Tx4kL1cvog4nxb"},{"block_id":"KVFxdUkzForrJ8xmRX4cRPMunad","block_type":12,"bullet":{"elements":[{"text_run":{"content":"可以設定經紀人的角色和權限，以及團隊的層級結構和管理關系。","text_element_style":{"bold":false,"inline_code":false,"italic":false,"strikethrough":false,"underline":false}}}],"style":{"align":1,"folded":false}},"parent_id":"EzcpdbKjDoWT1Tx4kL1cvog4nxb"},{"block_id":"SOEDd0xqUoHjrPxmcYnctdemnyd","block_type":13,"children":["SO2OdDbJIoOrkYxBJ4UcKSVxnIb","Prjqd4YFyocR1TxjqAqcoMbdnrc","HT1Ddw8ybokMHdx2VgSczO9onmd"],"ordered":{"elements":[{"text_run":{"content":"分成管理：","text_element_style":{"bold":false,"inline_code":false,"italic":false,"strikethrough":false,"underline":false}}}],"style":{"align":1,"folded":false}},"parent_id":"VWJRdn429ou7pGxspgicF05anvc"},{"block_id":"SO2OdDbJIoOrkYxBJ4UcKSVxnIb","block_type":12,"bullet":{"elements":[{"text_run":{"content":"該模塊用于管理經紀人與客戶之間的分成規則和分成計算。","text_element_style":{"bold":false,"inline_code":false,"italic":false,"strikethrough":false,"underline":false}}}],"style":{"align":1,"folded":false}},"parent_id":"SOEDd0xqUoHjrPxmcYnctdemnyd"},{"block_id":"Prjqd4YFyocR1TxjqAqcoMbdnrc","block_type":12,"bullet":{"elements":[{"text_run":{"content":"可以設定經紀人的分成比例，並根據客戶的交易量或投資收益計算相應的分成金額。","text_element_style":{"bold":false,"inline_code":false,"italic":false,"strikethrough":false,"underline":false}}}],"style":{"align":1,"folded":false}},"parent_id":"SOEDd0xqUoHjrPxmcYnctdemnyd"},{"block_id":"HT1Ddw8ybokMHdx2VgSczO9onmd","block_type":12,"bullet":{"elements":[{"text_run":{"content":"可以管理客戶的計費套餐及分成套餐。","text_element_style":{"bold":false,"inline_code":false,"italic":false,"strikethrough":false,"underline":false}}}],"style":{"align":1,"folded":false}},"parent_id":"SOEDd0xqUoHjrPxmcYnctdemnyd"},{"block_id":"HfpMdNZgBoEAzixVHF5cTwV0nsc","block_type":2,"parent_id":"VWJRdn429ou7pGxspgicF05anvc","text":{"elements":[{"text_run":{"content":"","text_element_style":{"bold":false,"inline_code":false,"italic":false,"strikethrough":false,"underline":false}}}],"style":{"align":1,"folded":false}}},{"block_id":"FhzNdYggNo3c9BxBKKfcxza6n2d","block_type":2,"parent_id":"VWJRdn429ou7pGxspgicF05anvc","text":{"elements":[{"text_run":{"content":"經紀人管理模塊提供了對經紀人與客戶關系的管理，經紀人和團隊的管理，以及分成管理等功能。","text_element_style":{"bold":false,"inline_code":false,"italic":false,"strikethrough":false,"underline":false}}}],"style":{"align":1,"folded":false}}}]}